Workbook

Sheet TABLE DASHBOARD
B1: ORDINATO | C1: DA ORDINARE
A2: DESIGN | B2: {=IFERROR(INDEX('JV RIEPILOGO'!$M:$M,MATCH($A2,'JV RIEPILOGO'!$B:$B,0)+1),"")} -> 24886974 | C2: =IFERROR(SUM(INDEX('JV RIEPILOGO'!$M:$M,MATCH($A2,'JV RIEPILOGO'!$B:$B,0)+2),INDEX('JV RIEPILOGO'!$M:$M,MATCH($A2,'JV RIEPILOGO'!$B:$B,0)+3)),"") -> 20703026
A3: CIVIL WORKS | B3: {=IFERROR(INDEX('JV RIEPILOGO'!$M:$M,MATCH($A3,'JV RIEPILOGO'!$B:$B,0)+1),"")} -> 53496524 | C3: =IFERROR(SUM(INDEX('JV RIEPILOGO'!$M:$M,MATCH($A3,'JV RIEPILOGO'!$B:$B,0)+2),INDEX('JV RIEPILOGO'!$M:$M,MATCH($A3,'JV RIEPILOGO'!$B:$B,0)+3)),"") -> 54613243
A4: ELECTRICAL WORKS | B4: {=IFERROR(INDEX('JV RIEPILOGO'!$M:$M,MATCH($A4,'JV RIEPILOGO'!$B:$B,0)+1),"")} -> 36070000 | C4: =IFERROR(SUM(INDEX('JV RIEPILOGO'!$M:$M,MATCH($A4,'JV RIEPILOGO'!$B:$B,0)+2),INDEX('JV RIEPILOGO'!$M:$M,MATCH($A4,'JV RIEPILOGO'!$B:$B,0)+3)),"") -> 22275340
A5: SANITARY WORKS AND FF | B5: {=IFERROR(INDEX('JV RIEPILOGO'!$M:$M,MATCH($A5,'JV RIEPILOGO'!$B:$B,0)+1),"")} -> 0 | C5: =IFERROR(SUM(INDEX('JV RIEPILOGO'!$M:$M,MATCH($A5,'JV RIEPILOGO'!$B:$B,0)+2),INDEX('JV RIEPILOGO'!$M:$M,MATCH($A5,'JV RIEPILOGO'!$B:$B,0)+3)),"") -> 21293319
A6: MECHANICAL AND TECHNOLOGICAL | B6: {=IFERROR(INDEX('JV RIEPILOGO'!$M:$M,MATCH($A6,'JV RIEPILOGO'!$B:$B,0)+1),"")} -> 1.5305376e+08 | C6: =IFERROR(SUM(INDEX('JV RIEPILOGO'!$M:$M,MATCH($A6,'JV RIEPILOGO'!$B:$B,0)+2),INDEX('JV RIEPILOGO'!$M:$M,MATCH($A6,'JV RIEPILOGO'!$B:$B,0)+3)),"") -> 1.0561288e+08
A7: COMMISSIONING | B7: {=IFERROR(INDEX('JV RIEPILOGO'!$M:$M,MATCH($A7,'JV RIEPILOGO'!$B:$B,0)+1),"")} -> 100000 | C7: =IFERROR(SUM(INDEX('JV RIEPILOGO'!$M:$M,MATCH($A7,'JV RIEPILOGO'!$B:$B,0)+2),INDEX('JV RIEPILOGO'!$M:$M,MATCH($A7,'JV RIEPILOGO'!$B:$B,0)+3)),"") -> 8400000
A8: ALIGNEMENT AND BACKUP | B8: {=IFERROR(INDEX('JV RIEPILOGO'!$M:$M,MATCH($A8,'JV RIEPILOGO'!$B:$B,0)+1),"")} -> 723162.81 | C8: =IFERROR(SUM(INDEX('JV RIEPILOGO'!$M:$M,MATCH($A8,'JV RIEPILOGO'!$B:$B,0)+2),INDEX('JV RIEPILOGO'!$M:$M,MATCH($A8,'JV RIEPILOGO'!$B:$B,0)+3)),"") -> 229618.19
A9: Total | B9: =SUM(B2:B8) -> 2.6833042e+08 | C9: =SUM(C2:C8) -> 2.3312743e+08
B10: =B9/'JV RIEPILOGO'!$M$32 -> 0.53510065 | C10: =C9/'JV RIEPILOGO'!$M$32 -> 0.46489935

Sheet JV RIEPILOGO
B1: ANALISI BUDGET WLOCLAWEK - MAG 26
C3: Budget Apertura | E3: B02 - Gennaio 2026 | G3: B7 - Febbraio 2026 | I3: B0 Riferimento (14) - Marzo 2026 | K3: B17 - Maggio 2026 | M3: B19 - Giugno 2026 | Q3: ORDINATO | R3: BUDGET | S3: 46143 | U3: 46174 | W3: 46204 | Y3: 46235 | AJ3: 46143 | AK3: 46174
B4: DESIGN | C4: ='1_Design'!C4+'1_Design'!C30 -> 45590000 | E4: =SUM(E5:E7) -> 45590000 | F4: =B4 -> DESIGN | G4: =SUM(G5:G7) -> 45590000 | I4: =SUM(I5:I7) -> 45590000 | K4: ='1_Design'!G4+'1_Design'!G30 -> 45590000 | M4: =SUM(M5:M7) -> 45590000 | Q4: =B4 -> DESIGN | R4: =M4 -> 45590000 | S4: 24397974 | T4: =S4/M4 -> 0.53516065 | U4: =M5 -> 24886974 | V4: =U4/M4 -> 0.54588669 | AI4: Costi Indiiretti | AJ4: =K34 -> 40036817 | AK4: 40357633
B5: Ordinato | C5: - | E5: 21990000 | F5: =B5 -> Ordinato | G5: 24270000 | H5: 0.8589476 | I5: ='1_Design'!$M$6 -> 24886974 | K5: ='1_Design'!G12+'1_Design'!G17+'1_Design'!G18+'1_Design'!G20+'1_Design'!G22+'1_Design'!G26+'1_Design'!G37 -> 24787974 | M5: ='1_Design'!$M$6 -> 24886974 | N5: =M5/M4 -> 0.54588669 | Q5: =B8 -> CIVIL WORKS | R5: =M8 -> 1.0810977e+08 | S5: 33404101 | T5: =S5/M8 -> 0.30898319 | U5: =M9 -> 53496524 | V5: =U5/M8 -> 0.49483526 | AI5: Costi di garanzia, difetti, imprevisti | AJ5: =K35 -> 22098535 | AK5: 22098535
B6: In negoziazione + buffer | C6: - | E6: =390000+17000000+150000 -> 17540000 | F6: =B6 -> In negoziazione + buffer | G6: 17890000 | H6: 0.042835399 | I6: ='1_Design'!$M$7 -> 17372026 | K6: ='1_Design'!G16+'1_Design'!G21+'1_Design'!G25+'1_Design'!G36+'1_Design'!G65 -> 17372026 | M6: ='1_Design'!$M$7 -> 17372026 | Q6: =B12 -> ELECTRICAL WORKS | R6: =M12 -> 58345340 | S6: 36070000 | T6: =S6/M12 -> 0.61821561 | U6: =M13 -> 36070000 | V6: =U6/M12 -> 0.61821561 | AI6: Totale Costi | AJ6: =AJ5+AJ4+R11 -> 5.6359321e+08 | AK6: =R11+AK4+AK5 -> 5.6391402e+08
B7: Da ordinare | C7: =C4 -> 45590000 | E7: 6060000 | F7: =B7 -> Da ordinare | G7: 3430000 | H7: 0.090889324 | I7: ='1_Design'!$M$8 -> 3331000 | K7: ='1_Design'!G19+'1_Design'!G23+'1_Design'!G24+'1_Design'!G32+'1_Design'!G41+'1_Design'!G45+'1_Design'!G49+'1_Design'!G53+'1_Design'!G57+'1_Design'!G61 -> 3430000 | M7: ='1_Design'!$M$8 -> 3331000 | Q7: =B16 -> SANITARY WORKS AND FF | R7: =M16 -> 21293319 | S7: 0 | T7: =S7/M16 -> 0 | U7: =M17 -> 0 | V7: =U7/M16 -> 0
B8: CIVIL WORKS | C8: ='2_Civil Work'!C3 -> 112409767 | E8: =SUM(E9:E11) -> 1.1240077e+08 | F8: =B8 -> CIVIL WORKS | G8: =SUM(G9:G11) -> 108109767 | I8: =SUM(I9:I11) -> 1.0810977e+08 | K8: ='2_Civil Work'!G3 -> 1.0810977e+08 | M8: =SUM(M9:M11) -> 1.0810977e+08 | Q8: =B20 -> MECHANICAL AND TECHNOLOGICAL | R8: =M20 -> 2.5866665e+08 | S8: 131227829 | T8: =S8/M20 -> 0.50732412 | U8: =M21 -> 1.5305376e+08 | V8: =U8/M20 -> 0.59170274 | AI8: Ricavi | AJ8: =K42 -> 627086000 | AK8: 627086000
B9: Ordinato | C9: - | E9: 9610714 | F9: =B9 -> Ordinato | G9: 25047291 | I9: ='2_Civil Work'!$M$5 -> 53496524 | K9: ='2_Civil Work'!G15+'2_Civil Work'!G20+'2_Civil Work'!G21+'2_Civil Work'!G22+'2_Civil Work'!G27+'2_Civil Work'!G34+'2_Civil Work'!G35+'2_Civil Work'!G36+'2_Civil Work'!G44+'2_Civil Work'!G47+'2_Civil Work'!G49+'2_Civil Work'!G50+'2_Civil Work'!G54+'2_Civil Work'!G57+'2_Civil Work'!G59+'2_Civil Work'!G60+'2_Civil Work'!G61+'2_Civil Work'!G69+'2_Civil Work'!G70+'2_Civil Work'!G72+'2_Civil Work'!G75+'2_Civil Work'!G121+'2_Civil Work'!G123+'2_Civil Work'!G149+'2_Civil Work'!G150 -> 53701520 | M9: ='2_Civil Work'!$M$5 -> 53496524 | N9: =M9/M8 -> 0.49483526 | Q9: =B24 -> COMMISSIONING | R9: =M24 -> 8500000 | S9: 100000 | T9: =S9/M24 -> 0.011764706 | U9: =M25 -> 100000 | V9: =U9/M24 -> 0.011764706 | AI9: Margine | AJ9: =AJ8-AJ6 -> 63492795 | AK9: =AK8-AK6 -> 63171979
B10: In negoziazione + buffer | C10: - | E10: =18700000+15345674 -> 34045674 | F10: =B10 -> In negoziazione + buffer | G10: 20510200 | I10: ='2_Civil Work'!$M$6 -> 16378807 | K10: ='2_Civil Work'!G12+'2_Civil Work'!G33+'2_Civil Work'!G42+'2_Civil Work'!G43+'2_Civil Work'!G46+'2_Civil Work'!G48+'2_Civil Work'!G53+'2_Civil Work'!G56+'2_Civil Work'!G68+'2_Civil Work'!G71+'2_Civil Work'!G74+'2_Civil Work'!G120+'2_Civil Work'!G122+'2_Civil Work'!G148 -> 16091828 | M10: ='2_Civil Work'!$M$6 -> 16378807 | Q10: =B28 -> ALIGNEMENT AND BACKUP | R10: =M28 -> 952781 | S10: =K29 -> 723162.81 | T10: =S10/M28 -> 0.75900213 | U10: =M29 -> 723162.81 | V10: =U10/M28 -> 0.75900213 | AJ10: =AJ9/AJ6 -> 0.11265713 | AK10: =AK9/AK6 -> 0.11202413
B11: Da ordinare | C11: =C8 -> 112409767 | E11: 68744379 | F11: =B11 -> Da ordinare | G11: 62552276 | I11: ='2_Civil Work'!$M$7 -> 38234436 | K11: ='2_Civil Work'!G26+'2_Civil Work'!G32+'2_Civil Work'!G55+'2_Civil Work'!G62+'2_Civil Work'!G63+'2_Civil Work'!G73+'2_Civil Work'!G79+'2_Civil Work'!G84+'2_Civil Work'!G85+'2_Civil Work'!G86+'2_Civil Work'!G87+'2_Civil Work'!G88+'2_Civil Work'!G89+'2_Civil Work'!G90+'2_Civil Work'!G91+'2_Civil Work'!G92+'2_Civil Work'!G93+'2_Civil Work'!G94+'2_Civil Work'!G95+'2_Civil Work'!G96+'2_Civil Work'!G101+'2_Civil Work'!G102+'2_Civil Work'!G103+'2_Civil Work'!G104+'2_Civil Work'!G105+'2_Civil Work'!G106+'2_Civil Work'!G110+'2_Civil Work'!G115+'2_Civil Work'!G116+'2_Civil Work'!G117+'2_Civil Work'!G118+'2_Civil Work'!G119+'2_Civil Work'!G124+'2_Civil Work'!G125+'2_Civil Work'!G126+'2_Civil Work'!G127+'2_Civil Work'!G128+'2_Civil Work'!G129+'2_Civil Work'!G130+'2_Civil Work'!G131+'2_Civil Work'!G132+'2_Civil Work'!G137+'2_Civil Work'!G138+'2_Civil Work'!G142+'2_Civil Work'!G147+'2_Civil Work'!G151+'2_Civil Work'!G155+'2_Civil Work'!G160+'2_Civil Work'!G161 -> 38316419 | M11: ='2_Civil Work'!$M$7 -> 38234436 | R11: =SUM(R4:R10) -> 5.0145785e+08 | S11: =SUM(S4:S10) -> 2.2592307e+08 | T11: =S11/M32 -> 0.45053251 | U11: =SUM(U4:U10) -> 2.6833042e+08 | V11: =U11/M32 -> 0.53510065
B12: ELECTRICAL WORKS | C12: ='3_Electrical Works'!C3 -> 58345340 | E12: =SUM(E13:E15) -> 58345340 | F12: =B12 -> ELECTRICAL WORKS | G12: =SUM(G13:G15) -> 58327340 | I12: =SUM(I13:I15) -> 58345340 | K12: ='3_Electrical Works'!G3 -> 58345340 | M12: =SUM(M13:M15) -> 58345340
B13: Ordinato | C13: - | E13: 0 | F13: =B13 -> Ordinato | G13: 38068200 | I13: ='3_Electrical Works'!$M$5 -> 36070000 | K13: ='3_Electrical Works'!G13+'3_Electrical Works'!G22+'3_Electrical Works'!G32 -> 36070000 | M13: ='3_Electrical Works'!$M$5 -> 36070000 | N13: =M13/M12 -> 0.61821561
B14: In negoziazione + buffer | C14: - | E14: 37400000 | F14: =B14 -> In negoziazione + buffer | G14: 0 | I14: ='3_Electrical Works'!$M$6 -> 2016200 | K14: =+'3_Electrical Works'!G12+'3_Electrical Works'!G31 -> 2016200 | M14: ='3_Electrical Works'!$M$6 -> 2016200
B15: Da ordinare | C15: =C12 -> 58345340 | E15: 20945340 | F15: =B15 -> Da ordinare | G15: 20259140 | I15: ='3_Electrical Works'!$M$7 -> 20259140 | K15: =+'3_Electrical Works'!G14+'3_Electrical Works'!G15+'3_Electrical Works'!G16+'3_Electrical Works'!G17+'3_Electrical Works'!G26+'3_Electrical Works'!G33+'3_Electrical Works'!G34 -> 20259140 | M15: ='3_Electrical Works'!$M$7 -> 20259140
B16: SANITARY WORKS AND FF | C16: ='4_Sanitary works and FF'!C3 -> 21293319 | E16: 21293319 | F16: =B16 -> SANITARY WORKS AND FF | G16: =SUM(G17:G19) -> 21293319 | I16: =SUM(I17:I19) -> 21293319 | K16: 21293319 | M16: =SUM(M17:M19) -> 21293319
B17: Ordinato | C17: - | E17: 0 | F17: =B17 -> Ordinato | G17: 0 | I17: ='4_Sanitary works and FF'!$M$6 -> 0 | K17: 0 | M17: ='4_Sanitary works and FF'!$M$6 -> 0 | N17: =M17/M16 -> 0
B18: In negoziazione + buffer | C18: - | E18: 0 | F18: =B18 -> In negoziazione + buffer | G18: 0 | I18: ='4_Sanitary works and FF'!$M$7 -> 0 | K18: 0 | M18: ='4_Sanitary works and FF'!$M$7 -> 0
B19: Da ordinare | C19: =C16 -> 21293319 | E19: 21293319 | F19: =B19 -> Da ordinare | G19: 21293319 | I19: ='4_Sanitary works and FF'!$M$8 -> 21293319 | K19: 21293319 | M19: ='4_Sanitary works and FF'!$M$8 -> 21293319
B20: MECHANICAL AND TECHNOLOGICAL | C20: ='5_Mechanical and technological'!C3 -> 258666646 | E20: =SUM(E21:E23) -> 2.5866665e+08 | F20: =B20 -> MECHANICAL AND TECHNOLOGICAL | G20: =SUM(G21:G23) -> 258666646 | I20: =SUM(I21:I23) -> 2.5866665e+08 | K20: 2.5866665e+08 | M20: =SUM(M21:M23) -> 2.5866665e+08
B21: Ordinato | C21: - | E21: 67510000 | F21: =B21 -> Ordinato | G21: 67810000 | I21: ='5_Mechanical and technological'!$M$5 -> 1.5305376e+08 | K21: ='5_Mechanical and technological'!G17+'5_Mechanical and technological'!G23+'5_Mechanical and technological'!G36+'5_Mechanical and technological'!G41+'5_Mechanical and technological'!G59+'5_Mechanical and technological'!G80+'5_Mechanical and technological'!G103+'5_Mechanical and technological'!G127 -> 1.3122783e+08 | M21: ='5_Mechanical and technological'!$M$5 -> 1.5305376e+08 | N21: =M21/M20 -> 0.59170274
B22: In negoziazione + buffer | C22: - | E22: =700000+300000 -> 1000000 | F22: =B22 -> In negoziazione + buffer | G22: 85700000 | I22: ='5_Mechanical and technological'!$M$6 -> 6615898 | K22: ='5_Mechanical and technological'!G35+'5_Mechanical and technological'!G79+'5_Mechanical and technological'!G102+'5_Mechanical and technological'!G126 -> 9211113.9 | M22: ='5_Mechanical and technological'!$M$6 -> 6615898
B23: Da ordinare | C23: =C20 -> 258666646 | E23: 1.9015665e+08 | F23: =B23 -> Da ordinare | G23: 105156646 | I23: ='5_Mechanical and technological'!$M$7 -> 98996985 | K23: =+'5_Mechanical and technological'!G12+'5_Mechanical and technological'!G18+'5_Mechanical and technological'!G24+'5_Mechanical and technological'!G25+'5_Mechanical and technological'!G26+'5_Mechanical and technological'!G27+'5_Mechanical and technological'!G28+'5_Mechanical and technological'!G29+'5_Mechanical and technological'!G30+'5_Mechanical and technological'!G42+'5_Mechanical and technological'!G43+'5_Mechanical and technological'!G44+'5_Mechanical and technological'!G45+'5_Mechanical and technological'!G49+'5_Mechanical and technological'!G53+'5_Mechanical and technological'!G58+'5_Mechanical and technological'!G60+'5_Mechanical and technological'!G61+'5_Mechanical and technological'!G66+'5_Mechanical and technological'!G67+'5_Mechanical and technological'!G68+'5_Mechanical and technological'!G72+'5_Mechanical and technological'!G77+'5_Mechanical and technological'!G78+'5_Mechanical and technological'!G81+'5_Mechanical and technological'!G82+'5_Mechanical and technological'!G83+'5_Mechanical and technological'!G84+'5_Mechanical and technological'!G85+'5_Mechanical and technological'!G86+'5_Mechanical and technological'!G87+'5_Mechanical and technological'!G88+'5_Mechanical and technological'!G89+'5_Mechanical and technological'!G90+'5_Mechanical and technological'!G91+'5_Mechanical and technological'!G92+'5_Mechanical and technological'!G94+'5_Mechanical and technological'!G95+'5_Mechanical and technological'!G96+'5_Mechanical and technological'!G97+'5_Mechanical and technological'!G98+'5_Mechanical and technological'!G107+'5_Mechanical and technological'!G112+'5_Mechanical and technological'!G113+'5_Mechanical and technological'!G114+'5_Mechanical and technological'!G115+'5_Mechanical and technological'!G116+'5_Mechanical and technological'!G117+'5_Mechanical and technological'!G118+'5_Mechanical and technological'!G119+'5_Mechanical and technological'!G120+'5_Mechanical and technological'!G121+'5_Mechanical and technological'!G128+'5_Mechanical and technological'!G129+'5_Mechanical and technological'!G130 -> 1.182277e+08 | M23: ='5_Mechanical and technological'!$M$7 -> 98996985
B24: COMMISSIONING | C24: ='6_ Commissioning'!C3 -> 8500000 | E24: =SUM(E25:E27) -> 8500000 | F24: =B24 -> COMMISSIONING | G24: =SUM(G25:G27) -> 8500000 | I24: =SUM(I25:I27) -> 8500000 | K24: =+'6_ Commissioning'!G3 -> 8500000 | M24: =SUM(M25:M27) -> 8500000
B25: Ordinato | C25: - | E25: 0 | F25: =B25 -> Ordinato | G25: 500000 | I25: ='6_ Commissioning'!$M$5 -> 100000 | K25: =+'6_ Commissioning'!G35 -> 100000 | M25: ='6_ Commissioning'!$M$5 -> 100000 | N25: =M25/M24 -> 0.011764706
B26: In negoziazione + buffer | C26: - | E26: 0 | F26: =B26 -> In negoziazione + buffer | G26: 0 | I26: ='6_ Commissioning'!$M$6 -> 400000 | K26: =+'6_ Commissioning'!G34 -> 400000 | M26: ='6_ Commissioning'!$M$6 -> 400000
B27: Da ordinare | C27: =C24 -> 8500000 | E27: 8500000 | F27: =B27 -> Da ordinare | G27: 8000000 | I27: ='6_ Commissioning'!$M$7 -> 8000000 | K27: =+'6_ Commissioning'!G12+'6_ Commissioning'!G13+'6_ Commissioning'!G14+'6_ Commissioning'!G15+'6_ Commissioning'!G20+'6_ Commissioning'!G21+'6_ Commissioning'!G22+'6_ Commissioning'!G23+'6_ Commissioning'!G24+'6_ Commissioning'!G25+'6_ Commissioning'!G26+'6_ Commissioning'!G30+'6_ Commissioning'!G39+'6_ Commissioning'!G43 -> 8000000 | M27: ='6_ Commissioning'!$M$7 -> 8000000
B28: ALIGNEMENT AND BACKUP | C28: ='7_Backup'!C3 -> 952781 | E28: =SUM(E29:E31) -> 952781 | F28: =B28 -> ALIGNEMENT AND BACKUP | G28: =SUM(G29:G31) -> 952781 | I28: =SUM(I29:I31) -> 952781 | K28: =+'7_Backup'!G3 -> 952781 | M28: =SUM(M29:M31) -> 952781
B29: Ordinato | C29: - | E29: =322212.81+400000 -> 722212.81 | F29: =B29 -> Ordinato | G29: 723163 | I29: ='7_Backup'!$M$5 -> 723162.81 | K29: ='7_Backup'!$M$5 -> 723162.81 | M29: ='7_Backup'!$M$5 -> 723162.81 | N29: =M29/M28 -> 0.75900213
B30: In negoziazione + buffer | C30: - | E30: 0 | F30: =B30 -> In negoziazione + buffer | G30: 0 | I30: ='7_Backup'!$M$6 -> 229618.19 | K30: =+'7_Backup'!G11+'7_Backup'!G16 -> 229618.19 | M30: ='7_Backup'!$M$6 -> 229618.19
B31: Da ordinare | C31: =C28 -> 952781 | E31: =216139.19+14429 -> 230568.19 | F31: =B31 -> Da ordinare | G31: 229618 | I31: ='7_Backup'!$M$9 -> 0 | K31: 0 | M31: ='7_Backup'!$M$9 -> 0
B32: Diretti | C32: =C4+C8+C12+C16+C20+C24+C28 -> 505757853 | E32: =E4+E8+E12+E16+E20+E24+E28 -> 5.0574885e+08 | F32: =B32 -> Diretti | G32: 5.0615785e+08 | I32: =I4+I8+I12+I16+I20+I24+I28 -> 5.0145785e+08 | K32: =+K28+K24+K20+K16+K12+K8+K4 -> 5.0145785e+08 | M32: =M4+M8+M12+M16+M20+M24+M28 -> 5.0145785e+08 | Q32: 40357633
B34: Indiretti | C34: ='0_Indirect'!C3 -> 40391014 | E34: ='0_Indirect'!D3 -> 40391014 | G34: 40386273 | I34: 40355205 | K34: 40036817 | M34: ='0_Indirect'!H3 -> 40357635
B35: Manutenzione | C35: 0 | E35: 22098535 | G35: 22098535 | I35: 22098535 | K35: 22098535 | M35: 22098535
B36: Totale Costi | C36: =C32+C34 -> 5.4614887e+08 | E36: =E32+E34+E35 -> 5.682384e+08 | G36: =G32+G34+G35 -> 5.6864266e+08 | I36: =I32+I34+I35 -> 5.6391159e+08 | K36: 5.6359321e+08 | M36: =M32+M34+M35 -> 5.6391402e+08 | O36: =M36/4.25 -> 1.3268565e+08 | P36: =O36*0.2 -> 26537131
C38: Totale ordinato | E38: =E29+E25+E21+E17+E13+E9+E5 -> 99832927 | F38: =E38/$E$32 -> 0.19739625 | G38: =G29+G25+G21+G17+G13+G9+G5 -> 156418654 | H38: 0.30494131 | I38: =I29+I25+I21+I17+I14+I9+I5 -> 2.3427662e+08 | J38: =I38/$I$32 -> 0.46719106 | K38: 2.6833042e+08 | M38: =M29+M25+M21+M17+M13+M9+M5 -> 2.6833042e+08 | N38: =M38/M32 -> 0.53510065
C39: Totale in neg + buffer | E39: =E6+E10+E14+E18+E22+E26+E30 -> 89985674 | G39: =G6+G10+G14+G18+G22+G26+G30 -> 124100200 | K39: 43012549 | M39: =M6+M10+M14+M18+M22+M26+M30 -> 43012549 | N39: =M39/M32 -> 0.085775003
C40: Totale da ordinare | E40: =E7+E11+E15+E19+E23+E27+E31 -> 3.1593025e+08 | F40: =E40/$E$32 -> 0.62467814 | G40: =G7+G11+G15+G19+G23+G27+G31 -> 220920999 | H40: 0.61558488 | I40: =I31+I27+I23+I19+I15+I11+I7 -> 1.9011488e+08 | J40: =I40/$I$32 -> 0.37912434 | K40: 1.9011488e+08 | M40: =M7+M11+M15+M19+M23+M27+M31 -> 1.9011488e+08 | N40: =M40/M32 -> 0.37912434
B42: Ricavi Base | C42: 631386000 | E42: 631386000 | G42: 6.31386e+08 | I42: 627086000 | K42: 627086000 | M42: 627086000 | O42: =M42/4.21 -> 1.4895154e+08 | P42: =O42*0.2 -> 29790309
B44: Margine | C44: =C42-C36 -> 85237133 | D44: =C44/C36 -> 0.15606941 | E44: =E42-E36 -> 63147598 | F44: =E44/E36 -> 0.1111287 | G44: 62743338 | H44: =G44/G36 -> 0.11033878 | I44: =I42-I36 -> 63174407 | J44: =I44/I36 -> 0.11202892 | K44: 63492795 | M44: =M42-M36 -> 63171977 | N44: =M44/M36 -> 0.11202413 | O44: =M44/4.25 -> 14863995 | P44: =O44*0.2 -> 2972798.9 | Q44: =P44/P36 -> 0.11202413

Sheet INTERNA
C2: 2025 | D2: 2026 | E2: oltre
B3: produzione | C3: =+C4+C5 -> 244.46201 | D3: =+D4+D5 -> 8888 | E3: =+E4+E5 -> 13414.595
B4: costi | C4: =+('[1]Włocławek Budget'!AM403+'[1]Włocławek Budget'!AM391)/4.2*0.15/1000 -> 220.03781 | D4: =+_xlfn.FLOOR.MATH(SUM('[1]Włocławek Budget'!AN403:AY403)/4.2*0.15/1000,1000) -> 8000 | E4: =+('[1]Włocławek Budget'!AB403/4.2*0.15/1000)-D4-C4 -> 12074.343
B5: margine | C5: =+C4*C6 -> 24.424197 | D5: =+D4*D6 -> 888 | E5: =+E4*E6 -> 1340.2521
B6: % | C6: =+D6 -> 0.111 | D6: 0.111 | E6: =+D6 -> 0.111

Sheet Report
C4: Bdgt apertura | D4: B02 - Gen26 | E4: B07 - Feb26 | P4: Consorzio | Q4: PORR 80%
B5: Costi diretti | C5: ='JV RIEPILOGO'!C32 -> 505757853 | D5: ='JV RIEPILOGO'!E32 -> 5.0574885e+08 | E5: ='JV RIEPILOGO'!I32 -> 5.0145785e+08 | Q5: TME 20%
B6: Costi indiretti | C6: ='JV RIEPILOGO'!C34 -> 40391014 | D6: ='JV RIEPILOGO'!E34 -> 40391014 | E6: ='JV RIEPILOGO'!I34 -> 40355205
B7: Contingency | C7: ='JV RIEPILOGO'!C35 -> 0 | D7: ='JV RIEPILOGO'!E35 -> 22098535 | E7: ='JV RIEPILOGO'!I35 -> 22098535 | P7: Cliente | Q7: PreZero
B8: Totale costi | C8: ='JV RIEPILOGO'!C36 -> 5.4614887e+08 | D8: ='JV RIEPILOGO'!E36 -> 5.682384e+08 | E8: ='JV RIEPILOGO'!I36 -> 5.6391159e+08
B9: Ricavi base | C9: ='JV RIEPILOGO'!C42 -> 631386000 | D9: ='JV RIEPILOGO'!E42 -> 631386000 | E9: ='JV RIEPILOGO'!I42 -> 627086000 | P9: Inizio progetto | Q9: 46052
B10: Margine | C10: ='JV RIEPILOGO'!C44 -> 85237133 | D10: ='JV RIEPILOGO'!E44 -> 63147598 | E10: ='JV RIEPILOGO'!I44 -> 63174407
B11: % | C11: =C10/C9 -> 0.13500004 | D11: =D10/D9 -> 0.10001425 | E11: =E10/E9 -> 0.10074281 | P11: Fine progetto | Q11: 46934
H15: COSTI DIRETTI (PLN)
I16: Apertura | J16: B07 | L16: Dettaglio costi diretti
H17: DESIGN | I17: ='JV RIEPILOGO'!C4 -> 45590000 | J17: ='JV RIEPILOGO'!I4 -> 45590000 | L17: Ordinato totale (senza TME) | M17: ='JV RIEPILOGO'!I5+'JV RIEPILOGO'!I9+'JV RIEPILOGO'!I13+'JV RIEPILOGO'!I17+'JV RIEPILOGO'!I21+'JV RIEPILOGO'!I25+'JV RIEPILOGO'!I29-M18 -> 1.9093042e+08 | N17: =M17/SUM($M$17:$M$21) -> #REF!
H18: CIVIL WORKS | I18: ='JV RIEPILOGO'!C8 -> 112409767 | J18: ='JV RIEPILOGO'!I8 -> 1.0810977e+08 | L18: Ordini a TME | M18: =Ordinato!C4 -> 77400000 | N18: =M18/SUM($M$17:$M$21) -> #REF!
H19: ELECTRICAL WORKS | I19: ='JV RIEPILOGO'!C12 -> 58345340 | J19: ='JV RIEPILOGO'!I12 -> 58345340 | L19: Negoziazioni totale | M19: ='JV RIEPILOGO'!I6+'JV RIEPILOGO'!I10+'JV RIEPILOGO'!I14+'JV RIEPILOGO'!I18+'JV RIEPILOGO'!I22+'JV RIEPILOGO'!I26+'JV RIEPILOGO'!I30 -> 43012549 | N19: =M19/SUM($M$17:$M$21) -> #REF!
H20: SANITARY WORKS AND FF | I20: ='JV RIEPILOGO'!E16 -> 21293319 | J20: ='JV RIEPILOGO'!I16 -> 21293319 | L20: Pianificato totale | M20: ='JV RIEPILOGO'!I7+'JV RIEPILOGO'!I11+'JV RIEPILOGO'!I15+'JV RIEPILOGO'!I19+'JV RIEPILOGO'!I23+'JV RIEPILOGO'!I27+'JV RIEPILOGO'!I31 -> 1.9011488e+08 | N20: =M20/SUM($M$17:$M$21) -> #REF!
H21: MECHANICAL AND TECHNOLOGICAL | I21: ='JV RIEPILOGO'!E20 -> 2.5866665e+08 | J21: ='JV RIEPILOGO'!I20 -> 2.5866665e+08 | L21: Buffer totale | M21: ='JV RIEPILOGO'!#REF!+'JV RIEPILOGO'!#REF!+'JV RIEPILOGO'!#REF!+'JV RIEPILOGO'!#REF!+'JV RIEPILOGO'!#REF!+'JV RIEPILOGO'!#REF!+'JV RIEPILOGO'!#REF! -> #REF! | N21: =M21/SUM($M$17:$M$21) -> #REF!
H22: COMMISSIONING | I22: ='JV RIEPILOGO'!C24 -> 8500000 | J22: ='JV RIEPILOGO'!I24 -> 8500000 | M22: =SUM(M17:M21) -> #REF!
H23: ALIGNEMENT AND BACKUP | I23: ='JV RIEPILOGO'!C28 -> 952781 | J23: ='JV RIEPILOGO'!I28 -> 952781
I24: =SUM(I17:I23) -> 5.0575785e+08 | J24: =SUM(J17:J23) -> 5.0145785e+08
H26: COSTI INDIRETTI (PLN) | L26: Lista ordini/ negoziazioni
I27: Apertura | J27: B07 | L27: Fornitore | M27: Sezione | N27: Item | O27: Descrizione | P27: Ordine | Q27: Importo
H28: STAFF | I28: ='0_Indirect'!C10 -> 29056500 | J28: ='0_Indirect'!E10 -> 29056500 | L28: =Ordinato!B28 -> FOROOM | M28: =Ordinato!C28 -> 1_Design | N28: =Ordinato!D28 -> 1.2.1 | O28: =Ordinato!E28 -> Detailed architectural, structural, sanitary and road designs | P28: =Ordinato!F28 -> 4502938068 | Q28: =Ordinato!G28 -> 12100000
H29: EQUIPMENT | I29: ='0_Indirect'!C18 -> 2404000 | J29: ='0_Indirect'!E18 -> 2404000 | L29: =Ordinato!B29 -> THYSSENKRUPP MATERIALS POLAND S.A. | M29: =Ordinato!C29 -> 2_Civil Works | N29: =Ordinato!D29 -> 2.5.1.1.1 | O29: =Ordinato!E29 -> Supply of reinforcing steel | P29: =Ordinato!F29 -> 4502938804 | Q29: =Ordinato!G29 -> 1821319
H30: CONSTRUCTION OFFICE | I30: ='0_Indirect'!C61 -> 4216821 | J30: ='0_Indirect'!E61 -> 4216821 | L30: =Ordinato!B30 -> THYSSENKRUPP MATERIALS POLAND S.A. | M30: =Ordinato!C30 -> 2_Civil Works | N30: =Ordinato!D30 -> 2.5.2.3.1 | O30: =Ordinato!E30 -> Supply of reinforcing steel | P30: =Ordinato!F30 -> 4502938804 | Q30: =Ordinato!G30 -> 1602761
H31: CONSTRUCTION | I31: ='0_Indirect'!C158 -> 3767010 | J31: ='0_Indirect'!E158 -> 3767010 | L31: =Ordinato!B31 -> MAR-KOP Marcin Mierzwa | M31: =Ordinato!C31 -> 2_Civil Works | N31: =Ordinato!D31 -> 2.2.1 | O31: =Ordinato!E31 -> Working platform for foundation works | P31: =Ordinato!F31 -> 4502939064 | Q31: =Ordinato!G31 -> 176673
H32: INSTALLATION / UNINSTALLATION OF CONSTRUCTION | I32: ='0_Indirect'!C222 -> 2278160 | J32: ='0_Indirect'!E222 -> 2278160 | L32: =Ordinato!B32 -> MAR-KOP Marcin Mierzwa | M32: =Ordinato!C32 -> 2_Civil Works | N32: =Ordinato!D32 -> 2.2.2 | O32: =Ordinato!E32 -> Earthworks | P32: =Ordinato!F32 -> 4502939064 | Q32: =Ordinato!G32 -> 2196542
H33: MISCELLANEOUS COSTS | I33: ='0_Indirect'!C270 -> 1600208 | J33: ='0_Indirect'!E270 -> 1600208 | L33: =Ordinato!B33 -> MAR-KOP Marcin Mierzwa | M33: =Ordinato!C33 -> 2_Civil Works | N33: =Ordinato!D33 -> 2.2.3 | O33: =Ordinato!E33 -> Earthworks – backfilling of retaining wall | P33: =Ordinato!F33 -> 4502939064 | Q33: =Ordinato!G33 -> 313419
H34: FINANCIAL COSTS | I34: ='0_Indirect'!C305 -> -2931684.9 | J34: ='0_Indirect'!E305 -> -2936425.7 | L34: =Ordinato!B34 -> MAR-KOP Marcin Mierzwa | M34: =Ordinato!C34 -> 7_Backup | N34: =Ordinato!D34 -> 7.1.1 | O34: =Ordinato!E34 -> Earthmoving robots ECR 3 | P34: =Ordinato!F34 -> 4502939064 | Q34: =Ordinato!G34 -> 322212.81
B35: Dati: Budget B07 di Febbraio 2026 | I35: =SUM(I28:I34) -> 40391014 | J35: =SUM(J28:J34) -> 40386273 | L35: =Ordinato!B35 -> KaBo | M35: =Ordinato!C35 -> 7_Backup | N35: =Ordinato!D35 -> 8.1.2 | O35: =Ordinato!E35 -> Obtaining ECR 4 decisions and permits | P35: =Ordinato!F35 -> 4502946461 | Q35: =Ordinato!G35 -> 400000
L36: =Ordinato!B36 -> ZAKŁAD SOZOTECHNIKI | M36: =Ordinato!C36 -> 1_Design | N36: =Ordinato!D36 -> 1.2.7.1 | O36: =Ordinato!E36 -> Preparation of an application for an integrated permit, together with all necessary documents. | P36: =Ordinato!F36 -> 4502966963 | Q36: =Ordinato!G36 -> 113000
L37: =Ordinato!B37 -> BARG | M37: =Ordinato!C37 -> 2_Civil Works | N37: =Ordinato!D37 -> 2.5.1.1.2 | O37: =Ordinato!E37 -> Concrete testing | P37: =Ordinato!F37 -> 4502968920 | Q37: =Ordinato!G37 -> 131560
L38: =Ordinato!B38 -> PROJBUD | M38: =Ordinato!C38 -> 7_Backup | N38: =Ordinato!D38 -> 8.1.1 | O38: =Ordinato!E38 -> Temporary traffic organization ECD 34 | P38: =Ordinato!F38 -> 4502971480 | Q38: =Ordinato!G38 -> 950
L39: =Ordinato!B43 -> Stump-Franki Sp. z o.o. | M39: =Ordinato!C43 -> 2_Civil Works | N39: =Ordinato!D43 -> 2.1.2 | O39: =Ordinato!E43 -> Diaphragm wall and barrettes part 1 | P39: =Ordinato!F43 -> ok | Q39: =Ordinato!G43 -> 3176000
L40: =Ordinato!B44 -> Stump-Franki Sp. z o.o. | M40: =Ordinato!C44 -> 2_Civil Works | N40: =Ordinato!D44 -> 2.1.3 | O40: =Ordinato!E44 -> Barrettes part 2 | P40: =Ordinato!F44 -> ok | Q40: =Ordinato!G44 -> 1124000
Q41: =SUM(Q28:Q40) -> 23478437
L43: =Ordinato!B52 -> TM.E. S.p.A - Termomeccanica Ecologia | M43: =Ordinato!C52 -> 5_Mechanical & Tech. | N43: =Ordinato!D52 -> 5.3.1 | O43: =Ordinato!E52 -> Furnace charging hopper + Furnace supporting steel structure + Complete grate fired furnace with waste feeding system + Hoppers under grate | P43: =Ordinato!F52 -> ok | Q43: =Ordinato!G52 -> 33755000
L44: =Ordinato!B53 -> TM.E. S.p.A - Termomeccanica Ecologia | M44: =Ordinato!C53 -> 5_Mechanical & Tech. | N44: =Ordinato!D53 -> 5.7.2 | O44: =Ordinato!E53 -> Flue gas treatment (FGT): Bag filter, Reactor, DeNOx, Flue gas condensation, Lime and activated carbon silos, dosing system | P44: =Ordinato!F53 -> ok | Q44: =Ordinato!G53 -> 33755000
L45: =Ordinato!B39 -> TME | M45: =Ordinato!C39 -> 1_Design | N45: =Ordinato!D39 -> 1.1 | O45: =Ordinato!E39 -> TME design | P45: =Ordinato!F39 -> ok | Q45: =Ordinato!G39 -> 9890000
Q46: =SUM(Q43:Q45) -> 77400000
L48: =Ordinato!B40 -> ELEKTROSERV - ZAP | M48: =Ordinato!C40 -> 1_Design | N48: =Ordinato!D40 -> 1.2.4 | O48: =Ordinato!E40 -> Electrical & I/C detailed design | P48: =Ordinato!F40 -> 0 | Q48: =Ordinato!G40 -> 1580000
L49: =Ordinato!B49 -> ELEKTROSERV - ZAP | M49: =Ordinato!C49 -> 3_Electrical Works | N49: =Ordinato!D49 -> 3.1.1.1 | O49: =Ordinato!E49 -> Delivery and installation of electrical equipment | P49: =Ordinato!F49 -> 0 | Q49: =Ordinato!G49 -> 28282000
L50: =Ordinato!B50 -> ELEKTROSERV - ZAP | M50: =Ordinato!C50 -> 3_Electrical Works | N50: =Ordinato!D50 -> 3.2.1 | O50: =Ordinato!E50 -> Teletechnical installations | P50: =Ordinato!F50 -> 0 | Q50: =Ordinato!G50 -> 2579200
L51: =Ordinato!B51 -> ELEKTROSERV - ZAP | M51: =Ordinato!C51 -> 3_Electrical Works | N51: =Ordinato!D51 -> 3.4.1.1 | O51: =Ordinato!E51 -> Automation system and instrumentation, communication networks and control room devices | P51: =Ordinato!F51 -> 0 | Q51: =Ordinato!G51 -> 5208800
L52: =Ordinato!B55 -> ELEKTROSERV - ZAP | M52: =Ordinato!C55 -> 6_Commissioning | N52: =Ordinato!D55 -> 6.4.1 | O52: =Ordinato!E55 -> Warranty extension for electrical works | P52: =Ordinato!F55 -> 0 | Q52: =Ordinato!G55 -> 100000
L53: =Ordinato!B41 -> MENOS | M53: =Ordinato!C41 -> 1_Design | N53: =Ordinato!D41 -> 1.2.5.1 | O53: =Ordinato!E41 -> Building and detailed design of the GPO/GPZ station | P53: =Ordinato!F41 -> 0 | Q53: =Ordinato!G41 -> 390000
L54: =Ordinato!B42 -> KaBo | M54: =Ordinato!C42 -> 1_Design | N54: =Ordinato!D42 -> 1.11 | O54: =Ordinato!E42 -> Obtaining decisions and permits | P54: =Ordinato!F42 -> 0 | Q54: =Ordinato!G42 -> 17000000
L55: =Ordinato!B46 -> BETARD | M55: =Ordinato!C46 -> 2_Civil Works | N55: =Ordinato!D46 -> 2.5.2.1.1 | O55: =Ordinato!E46 -> Reinforced concrete structure of the above-ground part of the B1 building - delivery and assembly of prefabricated elements | P55: =Ordinato!F46 -> 0 | Q55: =Ordinato!G46 -> 18700000
L56: =Ordinato!B47 -> BUSZREM | M56: =Ordinato!C47 -> 2_Civil Works | N56: =Ordinato!D47 -> 2.5.2.4 | O56: =Ordinato!E47 -> Supply of concrete mix with pumping service | P56: =Ordinato!F47 -> 0 | Q56: =Ordinato!G47 -> 29639
L57: =Ordinato!B48 -> BUSZREM | M57: =Ordinato!C48 -> 2_Civil Works | N57: =Ordinato!D48 -> 2.11.5.1 | O57: =Ordinato!E48 -> Delivery of concrete mix with pumping service | P57: =Ordinato!F48 -> 0 | Q57: =Ordinato!G48 -> 1040470
L58: =Ordinato!B45 -> BUSZREM | M58: =Ordinato!C45 -> 2_Civil Works | N58: =Ordinato!D45 -> 2.5.1.2 | O58: =Ordinato!E45 -> Supply of concrete mix with pumping service | P58: =Ordinato!F45 -> 0 | Q58: =Ordinato!G45 -> 3420000
L59: =Ordinato!B54 -> AS Rusztowania | M59: =Ordinato!C54 -> 5_Mechanical & Tech. | N59: =Ordinato!D54 -> 5.14.1.1 | O59: =Ordinato!E54 -> Scaffoldings | P59: =Ordinato!F54 -> 0 | Q59: =Ordinato!G54 -> 700000
Q60: =SUM(Q48:Q59) -> 79030109
L62: Dettaglio delle negoziazioni
L64: ELEKTROSERV - ZAP
L66: MENOS
L68: KaBo
L70: BUSZREM
L72: BETARD
L74: AS Rusztowania

Sheet Ordinato
B2: Totale costi | C2: ='JV RIEPILOGO'!I32 -> 5.0145785e+08
B3: Totale ordinato/negoziazione | C3: =SUM(C8:C23) -> 1.7990855e+08 | D3: =C3/C2 -> 0.35877102
B4: TME | C4: =C9+C8 -> 77400000 | D4: =C4/$C$3 -> 0.43021858
B5: Chiusi | C5: =G28+G29+G31+G30+G32+G33+G35+G34+G36+G37+G38 -> 19178437 | D5: =C5/$C$3 -> 0.10660103
B6: Negoziazione | C6: =G40+G41+G42+G43+G44+G45+G46+G47+G48+G49+G50+G51+G54+G55 -> 83330109 | D6: =C6/$C$3 -> 0.46318038
B8: TME | C8: =SUMIF($B$28:$B$5004,B8,$G$28:$G$5003) -> 9890000 | D8: =C8/$C$3 -> 0.054972375
B9: TM.E. S.p.A - Termomeccanica Ecologia | C9: =SUMIF($B$28:$B$5004,B9,$G$28:$G$5003) -> 67510000 | D9: =C9/$C$3 -> 0.37524621
B11: FOROOM | C11: =SUMIF($B$28:$B$5004,B11,$G$28:$G$5003) -> 12100000 | D11: =C11/$C$3 -> 0.067256394
B12: ELEKTROSERV - ZAP | C12: =SUMIF($B$28:$B$5004,B12,$G$28:$G$5003) -> 37750000 | D12: =C12/$C$3 -> 0.20982883 | E12: Lump sum
B13: MENOS | C13: =SUMIF($B$28:$B$5004,B13,$G$28:$G$5003) -> 390000 | D13: =C13/$C$3 -> 0.0021677681
B14: ZAKŁAD SOZOTECHNIKI | C14: =SUMIF($B$28:$B$5004,B14,$G$28:$G$5003) -> 113000 | D14: =C14/$C$3 -> 0.0006280969
B15: KaBo | C15: =SUMIF($B$28:$B$5004,B15,$G$28:$G$5003) -> 17400000 | D15: =C15/$C$3 -> 0.096715806
B16: Stump-Franki Sp. z o.o. | C16: =SUMIF($B$28:$B$5004,B16,$G$28:$G$5003) -> 4300000 | D16: =C16/$C$3 -> 0.023901032
B17: MAR-KOP Marcin Mierzwa | C17: =SUMIF($B$28:$B$5004,B17,$G$28:$G$5003) -> 3008846.8 | D17: =C17/$C$3 -> 0.016724313
B18: THYSSENKRUPP MATERIALS POLAND S.A. | C18: =SUMIF($B$28:$B$5004,B18,$G$28:$G$5003) -> 3424080 | D18: =C18/$C$3 -> 0.019032337
B19: BARG | C19: =SUMIF($B$28:$B$5004,B19,$G$28:$G$5003) -> 131560 | D19: =C19/$C$3 -> 0.00073126043
B20: BUSZREM | C20: =SUMIF($B$28:$B$5004,B20,$G$28:$G$5003) -> 4490109 | D20: =C20/$C$3 -> 0.024957731
B21: BETARD | C21: =SUMIF($B$28:$B$5004,B21,$G$28:$G$5003) -> 18700000 | D21: =C21/$C$3 -> 0.1039417
B22: AS Rusztowania | C22: =SUMIF($B$28:$B$5004,B22,$G$28:$G$5003) -> 700000 | D22: =C22/$C$3 -> 0.0038908658
B23: PROJBUD | C23: =SUMIF($B$28:$B$5004,B23,$G$28:$G$5003) -> 950 | D23: =C23/$C$3 -> 5.2804607e-06
B27: Fornitore | C27: Macroattività | D27: Item | E27: Descrizione | F27: Ordine | G27: Importo
B28: FOROOM | C28: 1_Design | D28: 1.2.1 | E28: Detailed architectural, structural, sanitary and road designs | F28: 4502938068 | G28: 12100000
B29: THYSSENKRUPP MATERIALS POLAND S.A. | C29: 2_Civil Works | D29: 2.5.1.1.1 | E29: Supply of reinforcing steel | F29: 4502938804 | G29: 1821319
B30: THYSSENKRUPP MATERIALS POLAND S.A. | C30: 2_Civil Works | D30: 2.5.2.3.1 | E30: Supply of reinforcing steel | F30: 4502938804 | G30: 1602761
B31: MAR-KOP Marcin Mierzwa | C31: 2_Civil Works | D31: 2.2.1 | E31: Working platform for foundation works | F31: 4502939064 | G31: 176673
B32: MAR-KOP Marcin Mierzwa | C32: 2_Civil Works | D32: 2.2.2 | E32: Earthworks | F32: 4502939064 | G32: 2196542
B33: MAR-KOP Marcin Mierzwa | C33: 2_Civil Works | D33: 2.2.3 | E33: Earthworks – backfilling of retaining wall | F33: 4502939064 | G33: 313419
B34: MAR-KOP Marcin Mierzwa | C34: 7_Backup | D34: 7.1.1 | E34: Earthmoving robots ECR 3 | F34: 4502939064 | G34: 322212.81
B35: KaBo | C35: 7_Backup | D35: 8.1.2 | E35: Obtaining ECR 4 decisions and permits | F35: 4502946461 | G35: 400000
B36: ZAKŁAD SOZOTECHNIKI | C36: 1_Design | D36: 1.2.7.1 | E36: Preparation of an application for an integrated permit, together with all necessary documents. | F36: 4502966963 | G36: 113000
B37: BARG | C37: 2_Civil Works | D37: 2.5.1.1.2 | E37: Concrete testing | F37: 4502968920 | G37: 131560 | H37: =SUM(G29:G37) -> 7077486.8
B38: PROJBUD | C38: 7_Backup | D38: 8.1.1 | E38: Temporary traffic organization ECD 34 | F38: 4502971480 | G38: 950
B39: TME | C39: 1_Design | D39: 1.1 | E39: TME design | F39: ok | G39: 9890000
B40: ELEKTROSERV - ZAP | C40: 1_Design | D40: 1.2.4 | E40: Electrical & I/C detailed design | G40: 1580000
B41: MENOS | C41: 1_Design | D41: 1.2.5.1 | E41: Building and detailed design of the GPO/GPZ station | G41: 390000
B42: KaBo | C42: 1_Design | D42: 1.11 | E42: Obtaining decisions and permits | G42: 17000000
B43: Stump-Franki Sp. z o.o. | C43: 2_Civil Works | D43: 2.1.2 | E43: Diaphragm wall and barrettes part 1 | F43: ok | G43: 3176000
B44: Stump-Franki Sp. z o.o. | C44: 2_Civil Works | D44: 2.1.3 | E44: Barrettes part 2 | F44: ok | G44: 1124000
B45: BUSZREM | C45: 2_Civil Works | D45: 2.5.1.2 | E45: Supply of concrete mix with pumping service | G45: 3420000
B46: BETARD | C46: 2_Civil Works | D46: 2.5.2.1.1 | E46: Reinforced concrete structure of the above-ground part of the B1 building - delivery and assembly of prefabricated elements | G46: 18700000
B47: BUSZREM | C47: 2_Civil Works | D47: 2.5.2.4 | E47: Supply of concrete mix with pumping service | G47: 29639
B48: BUSZREM | C48: 2_Civil Works | D48: 2.11.5.1 | E48: Delivery of concrete mix with pumping service | G48: 1040470 | H48: =SUM(G43:G48) -> 27490109
B49: ELEKTROSERV - ZAP | C49: 3_Electrical Works | D49: 3.1.1.1 | E49: Delivery and installation of electrical equipment | G49: 28282000
B50: ELEKTROSERV - ZAP | C50: 3_Electrical Works | D50: 3.2.1 | E50: Teletechnical installations | G50: 2579200
B51: ELEKTROSERV - ZAP | C51: 3_Electrical Works | D51: 3.4.1.1 | E51: Automation system and instrumentation, communication networks and control room devices | G51: 5208800
B52: TM.E. S.p.A - Termomeccanica Ecologia | C52: 5_Mechanical & Tech. | D52: 5.3.1 | E52: Furnace charging hopper + Furnace supporting steel structure + Complete grate fired furnace with waste feeding system + Hoppers under grate | F52: ok | G52: 33755000
B53: TM.E. S.p.A - Termomeccanica Ecologia | C53: 5_Mechanical & Tech. | D53: 5.7.2 | E53: Flue gas treatment (FGT): Bag filter, Reactor, DeNOx, Flue gas condensation, Lime and activated carbon silos, dosing system | F53: ok | G53: 33755000
B54: AS Rusztowania | C54: 5_Mechanical & Tech. | D54: 5.14.1.1 | E54: Scaffoldings | G54: 700000
B55: ELEKTROSERV - ZAP | C55: 6_Commissioning | D55: 6.4.1 | E55: Warranty extension for electrical works | G55: 100000

Sheet 0_Indirect
C2: BUDGET APERTURA | D2: BUDGET 02 | E2: BUDGET 07 | F2: BUDGET 14 (B0 approvato Mar 26) | G2: BUDGET 17 | H2: BUDGET 19 | J2: =SUM(J5:J7) -> 40357635
A3: 0 | B3: INDIRECT | C3: =C10+C18+C61+C158+C222+C270+C305 -> 40391014 | D3: =D10+D18+D61+D158+D222+D270+D305 -> 40391014 | E3: =E10+E18+E61+E158+E222+E270+E305 -> 40386273 | F3: =F10+F18+F61+F158+F222+F270+F305 -> 40355205 | G3: =G10+G18+G61+G158+G222+G270+G305 -> 40036817 | H3: =H10+H18+H61+H158+H222+H270+H305 -> 40357635
G4: =$F$3-G3 -> 318387.43 | H4: =$F$3-H3 -> -2430.3576
I5: Ordered | J5: =H13+H14+H22+H27+H28+H42+H43+H65+H67+H74+H79+H96+H107+H108+H109+H122+H135+H140+H146+H150+H166+H182+H187+H197+H201+H205+H226+H232+H233+H235+H236+H237+H244+H245+H255+H278+H279+H285+H300+H301+H314+H57+H55+H54+H53+H29+H30+H31+H32+H101+H167+H66+H254+H33+H34+H35+H36+H37+H44+H68+H69+H102+H123+H131+H141+H142+H168+H173+H188+H193+H210+H238+H256+H257+H258+H284+H294 -> 36343126
I6: Negotiation+buffer | J6: =+H26+H41+H52+H64+H73+H78+H95+H100+H106+H121+H139+H165+H172+H181+H186+H192+H231+H234+H253+H277+H283+H299+H312 -> 3545713
I7: Planned | J7: =+H21+H48+H83+H87+H91+H117+H127+H154+H161+H177+H209+H214+H249+H262+H266+H273+H289+H293+H298+H313+H318+H326+H330+H334+H338+H339 -> 468796.15
I8: (Buffer) | J8: =+H26+H41+H52+H64+H73+H78+H95+H100+H106+H121+H139+H165+H172+H181+H186+H192+H231+H234+H253+H277+H283+H299+H312 -> 3545713
A10: 1 | B10: STAFF | C10: =C15 -> 29056500 | D10: =D15 -> 29056500 | E10: =E15 -> 29056500 | F10: =F15 -> 29056500 | G10: =G15 -> 28713000 | H10: =H15 -> 29017400
G11: =G10-$F10 -> -343500 | H11: =H10-$F10 -> -39100
A13: 1.1 | B13: Remuneration PORR | C13: 18824500 | D13: 18824500 | E13: 18824500 | F13: 18824500 | G13: 18481000 | H13: 18824500 | I13: PORR kadra
A14: 1.2 | B14: Remuneration TME | C14: 10232000 | D14: 10232000 | E14: 10232000 | F14: 10232000 | G14: 10232000 | H14: 10192900 | I14: TME kadra
C15: =SUM(C13:C14) -> 29056500 | D15: =SUM(D13:D14) -> 29056500 | E15: =SUM(E13:E14) -> 29056500 | F15: =SUM(F13:F14) -> 29056500 | G15: =SUM(G13:G14) -> 28713000 | H15: =SUM(H13:H14) -> 29017400
G16: =G15-$F15 -> -343500 | H16: =H15-$F15 -> -39100
A18: 2 | B18: EQUIPMENT | C18: =C23+C38+C45+C49+C58 -> 2404000 | D18: =D23+D38+D45+D49+D58 -> 2404000 | E18: =E23+E38+E45+E49+E58 -> 2404000 | F18: =F23+F38+F45+F49+F58 -> 2389000 | G18: =G23+G38+G45+G49+G58 -> 2419000.6 | H18: =H23+H38+H45+H49+H58 -> 2404100
G19: =G18-$F18 -> 30000.65 | H19: =H18-$F18 -> 15100.014
A21: 2.1 | B21: Safety and health protection | C21: 96000 | D21: 96000 | E21: 96000 | F21: 96000 | G21: 96000 | H21: 90866.46
A22: 2.1.1 | B22: Lunches ECD 53 / 53rev 1 | C22: 0 | D22: 0 | E22: 0 | F22: 0 | G22: 0 | H22: 5233.54 | I22: MICHELIN
C23: =SUM(C21:C22) -> 96000 | D23: =SUM(D21:D22) -> 96000 | E23: =SUM(E21:E22) -> 96000 | F23: =SUM(F21:F22) -> 96000 | G23: =SUM(G21:G22) -> 96000 | H23: =SUM(H21:H22) -> 96100
G24: =G23-$F23 -> 0 | H24: =H23-$F23 -> 100
A26: 2.2 | B26: Small equipment hire | C26: 90000 | D26: 89038 | E26: 84038 | F26: 55834 | G26: 48734 | H26: 43734
A27: 2.2.1 | B27: Rental of a crane for driving a shovel ECD 3 | C27: 0 | D27: 962 | E27: 962 | F27: 962 | G27: 962 | H27: 962 | I27: BUDIZOL | J27: 4502914407
A28: 2.2.2 | B28: Rental of ECD 15 (Świnoujście - Włocławek) | C28: 0 | D28: 0 | E28: 2500 | F28: 2500 | G28: 2500 | H28: 2500 | I28: SILOGOSTIC | J28: 4502946426
A29: 2.2.3 | B29: Rental of ECD 15 rev 1 (Rzeszów - Włocławek) | C29: 0 | D29: 0 | E29: 2500 | F29: 2500 | G29: 2500 | H29: 2500 | I29: SILOGOSTIC | J29: 4502946426
A30: 2.2.4 | B30: Rental of ECD 15 rev 2 (Świnoujście - Włocławek) | C30: 0 | D30: 0 | E30: 0 | F30: 2400 | G30: 2400 | H30: 2400 | I30: SILOGOSTIC | J30: 4502946426
A31: 2.2.5 | B31: Rental of ECD 15 rev 3 (Rzeszów - Włocławek) | C31: 0 | D31: 0 | E31: 0 | F31: 1400 | G31: 1400 | H31: 1400 | I31: SILOGOSTIC | J31: 4502946426
A32: 2.2.6 | B32: Rental of ECD 44 generators | C32: 0 | D32: 0 | E32: 0 | F32: 23904 | G32: 23904 | H32: 23904 | I32: MOBIL SERWIS | J32: 4503007260
A33: 2.2.7 | B33: Rental of ECD 15 rev 4 (Lublin - Włocławek) | C33: 0 | D33: 0 | E33: 0 | F33: 500 | G33: 500 | H33: 500 | I33: SILOGOSTIC | J33: 4502946426
A34: 2.2.8 | B34: Rental of a drainage pump ECD 49 | C34: 0 | D34: 0 | E34: 0 | F34: 0 | G34: 4600 | H34: 4600 | I34: KLAUDIA | J34: 4503061913
A35: 2.2.9 | B35: Rental of ECD 15 rev 5 (Świnoujście - Włocławek) | C35: 0 | D35: 0 | E35: 0 | F35: 0 | G35: 2500 | H35: 2500 | I35: SILOGOSTIC | J35: 4502946426
A36: 2.2.10 | B36: Transport - ECD56 | C36: 0 | D36: 0 | E36: 0 | F36: 0 | G36: 0 | H36: 2700 | I36: FROGTRANS | J36: 4503121690
A37: 2.2.11 | B37: Transport - ECD56 rev 1 | C37: 0 | D37: 0 | E37: 0 | F37: 0 | G37: 0 | H37: 2300 | I37: FROGTRANS | J37: 4503121690
C38: =SUM(C26:C35) -> 90000 | D38: =SUM(D26:D35) -> 90000 | E38: =SUM(E26:E35) -> 90000 | F38: =SUM(F26:F35) -> 90000 | G38: =SUM(G26:G37) -> 90000 | H38: =SUM(H26:H37) -> 90000
G39: =G38-$F38 -> 0 | H39: =H38-$F38 -> 0
A41: 2.3 | B41: 30 T Truck Crane | C41: 314000 | D41: 314000 | E41: 123833 | F41: 123832.99 | G41: 123833 | H41: 123833
A42: 2.3.1 | B42: Open order - small building materials ECD 18 | C42: 0 | D42: 0 | E42: 50000.004 | F42: 50000.003 | G42: 50000.643 | H42: 50000.001 | I42: MAT-BUD | J42: 4502950515
A43: 2.3.2 | B43: Open order - small building materials ECD 19 | C43: 0 | D43: 0 | E43: 49999.996 | F43: 49999.997 | G43: 49999.997 | H43: 50000.003 | I43: HURTOWNIA TOOLS | J43: 4502950551
A44: 2.3.3 | B44: ECR 8 stationary cranes | C44: 0 | D44: 0 | E44: 90167 | F44: 90167.004 | G44: 90167.004 | H44: 90167.004 | I44: ŻURAWIE WIELKOPOLSKIE
C45: =SUM(C41:C44) -> 314000 | D45: =SUM(D41:D44) -> 314000 | E45: =SUM(E41:E44) -> 314000 | F45: =SUM(F41:F44) -> 313999.99 | G45: =SUM(G41:G44) -> 314000.64 | H45: =SUM(H41:H44) -> 314000.01
G46: =G45-$F45 -> 0.65 | H46: =H45-$F45 -> 0.014482759
A48: 2.4 | B48: Manitou Charger | C48: 544000 | D48: 544000 | E48: 544000 | F48: 544000 | G48: 544000 | H48: 544000
C49: =C48 -> 544000 | D49: =D48 -> 544000 | E49: =E48 -> 544000 | F49: =F48 -> 544000 | G49: =G48 -> 544000 | H49: =H48 -> 544000
G50: =G49-$F49 -> 0 | H50: =H49-$F49 -> 0
A52: 2.5 | B52: Stationary cranes | C52: 1360000 | D52: 1360000 | E52: 0 | F52: 1917 | G52: 16917 | H52: 1917
A53: 2.5.1 | B53: Water-sewage connection ECD 5 | C53: 0 | D53: 0 | E53: 101500 | F53: 101500 | G53: 101500 | H53: 101500 | I53: KRZYŚ | J53: 4502939080
A54: 2.5.1.1 | B54: Water-sewage connection ECD 5 rev 1 | C54: 0 | D54: 0 | E54: 21000 | F54: 21000 | G54: 21000 | H54: 21000 | I54: KRZYŚ aneks 1 | J54: 4502939080
A55: 2.5.2 | B55: Geodesy ECD 6 | C55: 0 | D55: 0 | E55: 155550 | F55: 140550 | G55: 155550 | H55: 155550 | I55: Geobet | J55: 4502939075
A56: 2.5.3 | B56: ECR 8 stationary cranes | C56: 0 | D56: 0 | E56: 1917 | F56: 0 | G56: 0 | H56: 0
A57: 2.5.4 | B57: ECR 8 stationary cranes | C57: 0 | D57: 0 | E57: 1080033 | F57: 1080033 | G57: 1080033 | H57: 1080033 | I57: ŻURAWIE WIELKOPOLSKIE
C58: =SUM(C52:C57) -> 1360000 | D58: =SUM(D52:D57) -> 1360000 | E58: =SUM(E52:E57) -> 1360000 | F58: =SUM(F52:F57) -> 1345000 | G58: =SUM(G52:G57) -> 1375000 | H58: =SUM(H52:H57) -> 1360000
G59: =G58-$F58 -> 30000 | H59: =H58-$F58 -> 15000
A61: 3 | B61: CONSTRUCTION OFFICE | C61: =C70+C75+C80+C84+C88+C92+C97+C103+C110+C114+C118+C124+C128+C132+C136+C143+C147+C151+C155 -> 4216821 | D61: =D70+D75+D80+D84+D88+D92+D97+D103+D110+D114+D118+D124+D128+D132+D136+D143+D147+D151+D155 -> 4216821 | E61: =E70+E75+E80+E84+E88+E92+E97+E103+E110+E114+E118+E124+E128+E132+E136+E143+E147+E151+E155 -> 4216821 | F61: =F70+F75+F80+F84+F88+F92+F97+F103+F110+F114+F118+F124+F128+F132+F136+F143+F147+F151+F155 -> 4230235.6 | G61: =G70+G75+G80+G84+G88+G92+G97+G103+G110+G114+G118+G124+G128+G132+G136+G143+G147+G151+G155 -> 4213421 | H61: =H70+H75+H80+H84+H88+H92+H97+H103+H110+H114+H118+H124+H128+H132+H136+H143+H147+H151+H155 -> 4244737.3
G62: =G61-$F61 -> -16814.64 | H62: =H61-$F61 -> 14501.693
A64: 3.1 | B64: Rental of office space or office containers | C64: 1984000 | D64: 1984000 | E64: 1150802 | F64: 1150802 | G64: 1145682 | H64: 1173395.4
A65: 3.1.1 | B65: Rental of office premises or office containers lease for 2 months ECD 2 | C65: 0 | D65: 0 | E65: 4080 | F65: 4080 | G65: 4080 | H65: 4080 | I65: CONTAINEX | J65: 4502914369
A66: 3.1.2 | B66: Rental of office premises or office containers ECD 20 | C66: 0 | D66: 0 | E66: 821840 | F66: 821840 | G66: 821840 | H66: 821840 | I66: PORR/PESA
A67: 3.1.3 | B67: Temporary office ECD 24 | C67: 0 | D67: 0 | E67: 7278 | F67: 7278 | G67: 7278 | H67: 7278 | I67: Staler Market | J67: 4502952746
A68: 3.1.4 | B68: Rental of office premises or office containers lease for 2 months ECD 2 rev 1 | C68: 0 | D68: 0 | E68: 0 | F68: 0 | G68: 720 | H68: 720 | I68: CONTAINEX | J68: 4502914369
A69: 3.1.5 | B69: Rental of office premises or office containers lease for 2 months ECD 2 rev 2 | C69: 0 | D69: 0 | E69: 0 | F69: 0 | G69: 0 | H69: 660 | I69: CONTAINEX | J69: 4502914369
C70: =SUM(C64:C69) -> 1984000 | D70: =SUM(D64:D69) -> 1984000 | E70: =SUM(E64:E69) -> 1984000 | F70: =SUM(F64:F69) -> 1984000 | G70: =SUM(G64:G69) -> 1979600 | H70: =SUM(H64:H69) -> 2007973.4
G71: =G70-$F70 -> -4400 | H71: =H70-$F70 -> 23973.39
A73: 3.2 | B73: Municipal waste disposal | C73: 114240 | D73: 114240 | E73: 64240 | F73: 64240 | G73: 64240 | H73: 64240
A74: 3.2.1 | B74: Municipal waste disposal ECD 12 | C74: 0 | D74: 0 | E74: 50000 | F74: 50000 | G74: 50000 | H74: 50000 | I74: SANIKO | J74: 4502943626
C75: =SUM(C73:C74) -> 114240 | D75: =SUM(D73:D74) -> 114240 | E75: =SUM(E73:E74) -> 114240 | F75: =SUM(F73:F74) -> 114240 | G75: =SUM(G73:G74) -> 114240 | H75: =SUM(H73:H74) -> 114240
G76: =G75-$F75 -> 0 | H76: =H75-$F75 -> 0
A78: 3.3 | B78: Electricity | C78: 219130 | D78: 219130 | E78: 169130 | F78: 169130 | G78: 169130 | H78: 169130
A79: 3.3.1 | B79: Electricity ECD 26 | C79: 0 | D79: 0 | E79: 50000 | F79: 50000 | G79: 50000 | H79: 53942.94 | I79: MPEC | J79: 4502138477
C80: =SUM(C78:C79) -> 219130 | D80: =SUM(D78:D79) -> 219130 | E80: =SUM(E78:E79) -> 219130 | F80: =SUM(F78:F79) -> 219130 | G80: =SUM(G78:G79) -> 219130 | H80: =SUM(H78:H79) -> 223072.94
G81: =G80-$F80 -> 0 | H81: =H80-$F80 -> 3942.94
A83: 3.4 | B83: Drinking water | C83: 108800 | D83: 108800 | E83: 108800 | F83: 108800 | G83: 109800 | H83: 108800
C84: =SUM(C83:C83) -> 108800 | D84: =SUM(D83:D83) -> 108800 | E84: =SUM(E83:E83) -> 108800 | F84: =SUM(F83:F83) -> 108800 | G84: =SUM(G83:G83) -> 109800 | H84: =SUM(H83:H83) -> 108800
G85: =G84-$F84 -> 1000 | H85: =H84-$F84 -> 0
A87: 3.5 | B87: Sewage costs/ septic tank disposal/ | C87: 157760 | D87: 157760 | E87: 157760 | F87: 157760 | G87: 157760 | H87: 157760
C88: =SUM(C87:C87) -> 157760 | D88: =SUM(D87:D87) -> 157760 | E88: =SUM(E87:E87) -> 157760 | F88: =SUM(F87:F87) -> 157760 | G88: =SUM(G87:G87) -> 157760 | H88: =SUM(H87:H87) -> 157760
G89: =G88-$F88 -> 0 | H89: =H88-$F88 -> 0
A91: 3.6 | B91: Monthly internet costs | C91: 179520 | D91: 179520 | E91: 179520 | F91: 179520 | G91: 179520 | H91: 179520
C92: =SUM(C91:C91) -> 179520 | D92: =SUM(D91:D91) -> 179520 | E92: =SUM(E91:E91) -> 179520 | F92: =SUM(F91:F91) -> 179520 | G92: =SUM(G91:G91) -> 179520 | H92: =SUM(H91:H91) -> 179520
G93: =G92-$F92 -> 0 | H93: =H92-$F92 -> 0
A95: 3.7 | B95: Office supplies | C95: 174080 | D95: 174080 | E95: 84080 | F95: 84080 | G95: 84080 | H95: 84080
A96: 3.7.1 | B96: ECD 32 Office Supplies | C96: 0 | D96: 0 | E96: 90000 | F96: 90000 | G96: 90000 | H96: 90000.003 | I96: ABIS
C97: =SUM(C95:C96) -> 174080 | D97: =SUM(D95:D96) -> 174080 | E97: =SUM(E95:E96) -> 174080 | F97: =SUM(F95:F96) -> 174080 | G97: =SUM(G95:G96) -> 174080 | H97: =SUM(H95:H96) -> 174080
G98: =G97-$F97 -> 0 | H98: =H97-$F97 -> 0.0034482779
A100: 3.8 | B100: Cleaning | C100: 282880 | D100: 282880 | E100: 104680 | F100: 74680 | G100: 74680 | H100: 74680
A101: 3.8.1 | B101: Cleaning the ECD 35 back room | C101: 0 | D101: 0 | E101: 178200 | F101: 178200 | G101: 178200 | H101: 178200 | I101: CERBER | J101: 4502976093
A102: 3.8.2 | B102: Sanitary Wholesaler - Open Order ECD 40 | C102: 0 | D102: 0 | E102: 0 | F102: 30000 | G102: 30000 | H102: 30000 | I102: ATMOMAT | J102: 4502983951
C103: =SUM(C100:C101) -> 282880 | D103: =SUM(D100:D101) -> 282880 | E103: =SUM(E100:E101) -> 282880 | F103: =SUM(F100:F102) -> 282880 | G103: =SUM(G100:G102) -> 282880 | H103: =SUM(H100:H102) -> 282880
G104: =G103-$F103 -> 0 | H104: =H103-$F103 -> 0
A106: 3.9 | B106: Coffee/tea | C106: 84320 | D106: 84320 | E106: 26702.22 | F106: 26702.22 | G106: 26702.22 | H106: 26702.22
A107: 3.9.1 | B107: Coffee Tea - ECD 8 kick off meeting | C107: 0 | D107: 0 | E107: 6277.78 | F107: 6277.78 | G107: 6277.78 | H107: 6277.78 | I107: KA-BO Borkowski | J107: 4502940616
A108: 3.9.2 | B108: Coffee tea - meeting 29.01.2026 ECD 23 | C108: 0 | D108: 0 | E108: 1340 | F108: 1340 | G108: 1340 | H108: 1340 | I108: Hotel Aleksander | J108: 4502955423
A109: 3.9.3 | B109: Lease of ECD 28 coffee machine | C109: 0 | D109: 0 | E109: 50000 | F109: 50000 | G109: 50000 | H109: 50000 | I109: COFFE PARTNER | J109: 4502960536
C110: =SUM(C106:C109) -> 84320 | D110: =SUM(D106:D109) -> 84320 | E110: =SUM(E106:E109) -> 84320 | F110: =SUM(F106:F109) -> 84320 | G110: =SUM(G106:G109) -> 84320 | H110: =SUM(H106:H109) -> 84320
G111: =G110-$F110 -> 0 | H111: =H110-$F110 -> 0
A113: 3.10 | B113: Representation costs | C113: 0 | D113: 0 | E113: 0 | F113: 0 | G113: 0 | H113: 0
C114: =SUM(C113:C113) -> 0 | D114: =SUM(D113:D113) -> 0 | E114: =SUM(E113:E113) -> 0 | F114: =SUM(F113:F113) -> 0 | G114: =SUM(G113:G113) -> 0 | H114: =SUM(H113:H113) -> 0
G115: =G114-$F114 -> 0 | H115: =H114-$F114 -> 0
A117: 3.11 | B117: Office costs PORR (with PC service) | C117: 500480 | D117: 500480 | E117: 500480 | F117: 500480 | G117: 500480 | H117: 500480
C118: =C117 -> 500480 | D118: =D117 -> 500480 | E118: =E117 -> 500480 | F118: =F117 -> 500480 | G118: =G117 -> 500480 | H118: =H117 -> 500480
G119: =G118-$F118 -> 0 | H119: =H118-$F118 -> 0
A121: 3.12 | B121: Office equipment | C121: 43520 | D121: 43520 | E121: 29190 | F121: 29190 | G121: 29190 | H121: 29190
A122: 3.12.1 | B122: multimedia equipment ECD 33 | C122: 0 | D122: 0 | E122: 11980 | F122: 11980 | G122: 11980 | H122: 11980 | I122: AV Kreator | J122: 4502971588
...

Sheet 1_Design
C2: BUDGET APERTURA | D2: BUDGET 02 | E2: BUDGET 07 | F2: BUDGET 14 (B0 approvato Mar 26) | G2: BUDGET 17 | H2: BUDGET 19 | I2: ORDINATO | J2: DA ORDINARE EXTRA | K2: TOTALE CON FORECAST
C3: =C4+C30 -> 45590000 | D3: =D4+D30 -> 45590000 | E3: =E4+E30 -> 45990000 | K3: =K4+K30 -> 45590000 | M3: =SUM(M6:M9) -> 45590000
A4: 1 | B4: DESIGN | C4: =C13+C27 -> 27170000 | D4: =D13+D27 -> 27170000 | E4: =E13+E27 -> 27170000 | F4: =F13+F27 -> 27170000 | G4: =G13+G27 -> 27170000 | H4: =H13+H27 -> 27170000 | I4: =I13+I27+I33+I38+I42+I46 -> 0 | J4: =J13+J27+J33+J38+J42+J46 -> 0 | K4: =K13+K27 -> 27170000
G5: =G4-$F$4 -> 0.0052067265 | H5: =H4-$F$4 -> 0.0051454566 | K5: =K4-$F$4 -> 0.0051454566
L6: Ordered | M6: =H12+H17+H37+H26+H18+H20+H22+H24 -> 24886974
L7: Negotiation | M7: =H65+H16+H21+H25+H36 -> 17372026
D8: SAVINGS | E8: =D14+D34 -> 0 | F8: =E14+E34 -> 0 | G8: =F14+F34 -> 0 | H8: =G14+G34 -> -0.0033339988 | J8: SAVINGS | L8: Planned | M8: =H19+H23+H32+H41+H45+H49+H53+H57+H61 -> 3331000
D9: EXTRA | E9: =D47 -> 0 | F9: =E47 -> 0 | G9: =F47 -> 0 | H9: =G47 -> 0 | J9: EXTRA | L9: Extra | M9: =J4 -> 0
L10: (Buffer) | M10: =H16+H21+H25+H36 -> 372026
A12: 1.1 | B12: TME design | C12: 9890000 | D12: 9890000 | E12: 9890000 | F12: 9890000 | G12: 9890000 | H12: 9890000 | K12: =SUM(H12:J12) -> 9890000 | L12: TME
C13: =SUM(C12:C12) -> 9890000 | D13: =SUM(D12:D12) -> 9890000 | E13: =SUM(E12:E12) -> 9890000 | F13: =SUM(F12:F12) -> 9890000 | G13: =SUM(G12:G12) -> 9890000 | H13: =SUM(H12:H12) -> 9890000 | I13: =SUM(I12:I12) -> 0 | J13: =SUM(J12:J12) -> 0 | K13: =SUM(K12:K12) -> 9890000
G14: =$F13-G13 -> -0.0033339988 | H14: =$F13-H13 -> 0 | K14: =$F13-K13 -> 0
A16: 1.2 | B16: Detailed architectural, structural, sanitary and road designs | C16: 12200000 | D16: 100000 | E16: 100000 | F16: 100000 | G16: 100000 | H16: 100000 | K16: =SUM(H16:J16) -> 100000
A17: 1.2.1 | B17: Detailed architectural, structural, sanitary and road designs - ECR 1 | C17: 0 | D17: 12100000 | E17: 12100000 | F17: 12100000 | G17: 12100000 | H17: 12100000 | K17: =SUM(H17:J17) -> 12100000 | L17: FOROOM | M17: 4502938068
A18: 1.2.2 | B18: Detailed design: boiler support steel structure and equipment support structures - ECD 41 | C18: 500000 | D18: 500000 | E18: 500000 | F18: 500000 | G18: 500000 | H18: 500000 | K18: =SUM(H18:J18) -> 500000 | L18: ODS | M18: Ok
A19: 1.2.3 | B19: Detailed design: fire-fighting system | C19: 260000 | D19: 260000 | E19: 260000 | F19: 260000 | G19: 260000 | H19: 260000 | K19: =SUM(H19:J19) -> 260000
A20: 1.2.4 | B20: Electrical & I/C detailed design | C20: 1580000 | D20: 1580000 | E20: 1580000 | F20: 1580000 | G20: 1580000 | H20: 1580000 | K20: =SUM(H20:J20) -> 1580000 | L20: ELEKTROSERV - ZAP | M20: Ok
A21: 1.2.5 | B21: Building and detailed design of the GPO/GPZ station | C21: 440000 | D21: 50000 | E21: 50000 | F21: 50000 | G21: 50000 | H21: 50000 | K21: =SUM(H21:J21) -> 50000
A22: 1.2.5.1 | B22: Building and detailed design of the GPO/GPZ station | C22: 0 | D22: 390000 | E22: 390000 | F22: 390000 | G22: 390000 | H22: 390000 | K22: =SUM(H22:J22) -> 390000 | L22: MENOS | M22: Ok
A23: 1.2.6 | B23: Piping and ducts design | C23: 2000000 | D23: 2000000 | E23: 2000000 | F23: 2000000 | G23: 2000000 | H23: 1901000 | K23: =SUM(H23:J23) -> 1901000
A24: 1.2.6.1 | B24: Air and flue gas ducts design - ECR20 | C24: 0 | D24: 0 | E24: 0 | F24: 0 | G24: 0 | H24: 99000 | K24: =SUM(H24:J24) -> 99000 | L24: ODS | M24: 4502993588
A25: 1.2.7 | B25: Other documentation, opinions, agreements, permits, provisions, approvals and decisions necessary for the design, execution of the Works and commissioning of the investment (concession documentation for the generation of electricity and heat from a renewable energy source, ITPOE operating permit, integrated permit, geological designs and documentation, commissioning designs, operating instructions, etc.). | C25: 300000 | D25: 300000 | E25: 187000 | F25: 187000 | G25: 187000 | H25: 187000 | K25: =SUM(H25:J25) -> 187000
A26: 1.2.7.1 | B26: Preparation of the application for the issuance of an integrated permit with all necessary documents ECD 27 | C26: 0 | D26: 0 | E26: 113000 | F26: 113000 | G26: 113000 | H26: 113000 | K26: =SUM(H26:J26) -> 113000 | L26: ZAKŁAD SOZOTECHNIKI | M26: 4502966963
C27: =SUM(C16:C26) -> 17280000 | D27: =SUM(D16:D26) -> 17280000 | E27: =SUM(E16:E26) -> 17280000 | F27: =SUM(F16:F26) -> 17280000 | G27: =SUM(G16:G26) -> 17280000 | H27: =SUM(H16:H26) -> 17280000 | I27: =SUM(I16:I26) -> 0 | J27: =SUM(J16:J26) -> 0 | K27: =SUM(K16:K26) -> 17280000
G28: =$F27-G27 -> -0.0018727295 | H28: =$F27-H27 -> -0.0051454566 | K28: =$F27-K27 -> -0.0051454566
B30: Service companies | C30: =C33+C38+C42+C46+C50+C54+C58+C62+C66 -> 18420000 | D30: =D33+D38+D42+D46+D50+D54+D58+D62+D66 -> 18420000 | E30: =E33+E38+E42+E46+E50+E54+E58+E62+E66 -> 18820000 | F30: =F33+F38+F42+F46+F50+F54+F58+F62+F66 -> 18420000 | G30: =G33+G38+G42+G46+G50+G54+G58+G62+G66 -> 18420000 | H30: =H33+H38+H42+H46+H50+H54+H58+H62+H66 -> 18420000 | K30: =K33+K38+K42+K46+K50+K54+K58+K62+K66 -> 18420000
A32: 1.3 | B32: Noise Analysis and noise protection design | C32: 100000 | D32: 100000 | E32: 100000 | F32: 100000 | G32: 100000 | H32: 100000 | K32: =SUM(H32:J32) -> 100000
C33: =SUM(C32:C32) -> 100000 | D33: =SUM(D32:D32) -> 100000 | E33: =SUM(E32:E32) -> 100000 | F33: =SUM(F32:F32) -> 100000 | G33: =SUM(G32:G32) -> 100000 | H33: =SUM(H32:H32) -> 100000 | I33: =SUM(I32:I32) -> 0 | J33: =SUM(J32:J32) -> 0 | K33: =SUM(K32:K32) -> 100000
G34: =$F33-G33 -> 0 | H34: =$F33-H33 -> 0 | K34: =$F33-K33 -> 0
A36: 1.4 | B36: HAZOP study and SIL analysis | C36: 250000 | D36: 250000 | E36: 250000 | F36: 35026 | G36: 35026 | H36: 35026 | K36: =SUM(H36:J36) -> 35026
A37: 1.4.1 | B37: HAZOP study and SIL analysis | F37: 214974 | G37: 214974 | H37: 214974 | K37: =SUM(H37:J37) -> 214974 | L37: UDT CERT | M37: 4503027816
C38: =SUM(C36:C37) -> 250000 | D38: =SUM(D36:D37) -> 250000 | E38: =SUM(E36:E37) -> 250000 | F38: =SUM(F36:F37) -> 250000 | G38: =SUM(G36:G37) -> 250000 | H38: =SUM(H36:H37) -> 250000 | I38: =SUM(I36:I37) -> 0 | J38: =SUM(J36:J37) -> 0 | K38: =SUM(K36:K37) -> 250000
G39: =$F38-G38 -> 0 | H39: =$F38-H38 -> 0 | K39: =$F38-K38 -> 0
A41: 1.5 | B41: Fire safety instructions | C41: 100000 | D41: 100000 | E41: 100000 | F41: 100000 | G41: 100000 | H41: 100000 | K41: =SUM(H41:J41) -> 100000
C42: =SUM(C41:C41) -> 100000 | D42: =SUM(D41:D41) -> 100000 | E42: =SUM(E41:E41) -> 100000 | F42: =SUM(F41:F41) -> 100000 | G42: =SUM(G41:G41) -> 100000 | H42: =SUM(H41:H41) -> 100000 | I42: =SUM(I41:I41) -> 0 | J42: =SUM(J41:J41) -> 0 | K42: =SUM(K41:K41) -> 100000
G43: =$F42-G42 -> 0 | H43: =$F42-H42 -> 0 | K43: =$F42-K42 -> 0
A45: 1.6 | B45: Explosion hazard assessment | C45: 120000 | D45: 120000 | E45: 120000 | F45: 120000 | G45: 120000 | H45: 120000 | K45: =SUM(H45:J45) -> 120000
C46: =SUM(C45:C45) -> 120000 | D46: =SUM(D45:D45) -> 120000 | E46: =SUM(E45:E45) -> 120000 | F46: =SUM(F45:F45) -> 120000 | G46: =SUM(G45:G45) -> 120000 | H46: =SUM(H45:H45) -> 120000 | I46: =SUM(I45:I45) -> 0 | J46: =SUM(J45:J45) -> 0 | K46: =SUM(K45:K45) -> 120000
G47: =$F46-G46 -> 0 | H47: =$F46-H46 -> 0 | K47: =$F46-K46 -> 0
A49: 1.7 | B49: Technical Consultant for certification and for complying with European Directives | C49: 100000 | D49: 100000 | E49: 100000 | F49: 100000 | G49: 100000 | H49: 100000.01 | K49: =SUM(H49:J49) -> 100000.01
C50: =SUM(C49:C49) -> 100000 | D50: =SUM(D49:D49) -> 100000 | E50: =SUM(E49:E49) -> 100000 | F50: =SUM(F49:F49) -> 100000 | G50: =SUM(G49:G49) -> 100000 | H50: =SUM(H49:H49) -> 100000.01 | I50: =SUM(I49:I49) -> 0 | J50: =SUM(J49:J49) -> 0 | K50: =SUM(K49:K49) -> 100000.01
G51: =$F50-G50 -> -0.0046153846 | H51: =$F50-H50 -> -0.0069230769 | K51: =$F50-K50 -> -0.0069230769
A53: 1.8 | B53: Notification Bodies | C53: 350000 | D53: 350000 | E53: 350000 | F53: 350000 | G53: 350000 | H53: 350000 | K53: =SUM(H53:J53) -> 350000
C54: =SUM(C53:C53) -> 350000 | D54: =SUM(D53:D53) -> 350000 | E54: =SUM(E53:E53) -> 350000 | F54: =SUM(F53:F53) -> 350000 | G54: =SUM(G53:G53) -> 350000 | H54: =SUM(H53:H53) -> 350000 | I54: =SUM(I53:I53) -> 0 | J54: =SUM(J53:J53) -> 0 | K54: =SUM(K53:K53) -> 350000
G55: =$F54-G54 -> 0 | H55: =$F54-H54 -> 0.0018181818 | K55: =$F54-K54 -> 0.0018181818
A57: 1.9 | B57: Translations (Polish / English) | C57: 250000 | D57: 250000 | E57: 250000 | F57: 250000 | G57: 250000 | H57: 250000 | K57: =SUM(H57:J57) -> 250000
C58: =SUM(C57:C57) -> 250000 | D58: =SUM(D57:D57) -> 250000 | E58: =SUM(E57:E57) -> 250000 | F58: =SUM(F57:F57) -> 250000 | G58: =SUM(G57:G57) -> 250000 | H58: =SUM(H57:H57) -> 250000 | I58: =SUM(I57:I57) -> 0 | J58: =SUM(J57:J57) -> 0 | K58: =SUM(K57:K57) -> 250000
G59: =$F58-G58 -> -0.00298 | H59: =$F58-H58 -> -0.00298 | K59: =$F58-K58 -> -0.00298
A61: 1.10 | B61: NC Rfg certification | C61: 150000 | D61: 150000 | E61: 150000 | F61: 150000 | G61: 150000 | H61: 150000 | K61: =SUM(H61:J61) -> 150000
C62: =SUM(C61:C61) -> 150000 | D62: =SUM(D61:D61) -> 150000 | E62: =SUM(E61:E61) -> 150000 | F62: =SUM(F61:F61) -> 150000 | G62: =SUM(G61:G61) -> 150000 | H62: =SUM(H61:H61) -> 150000 | I62: =SUM(I61:I61) -> 0 | J62: =SUM(J61:J61) -> 0 | K62: =SUM(K61:K61) -> 150000
G63: =$F62-G62 -> 0 | H63: =$F62-H62 -> 0 | K63: =$F62-K62 -> 0
A65: 1.11 | B65: Obtaining decisions and permits - ECR 4 | C65: 17000000 | D65: 17000000 | E65: 17400000 | F65: 17000000 | G65: 17000000 | H65: 17000000 | K65: =SUM(H65:J65) -> 17000000 | L65: KaBo | M65: 4502946461
C66: =SUM(C65:C65) -> 17000000 | D66: =SUM(D65:D65) -> 17000000 | E66: =SUM(E65:E65) -> 17400000 | F66: =SUM(F65:F65) -> 17000000 | G66: =SUM(G65:G65) -> 17000000 | H66: =SUM(H65:H65) -> 17000000 | I66: =SUM(I65:I65) -> 0 | J66: =SUM(J65:J65) -> 0 | K66: =SUM(K65:K65) -> 17000000
G67: =$F66-G66 -> 0 | H67: =$F66-H66 -> 0 | K67: =$F66-K66 -> 0

Sheet 2_Civil Work
C2: BUDGET APERTURA | D2: BUDGET 02 | E2: BUDGET 07 | F2: BUDGET 14 (B0 approvato Mar 26) | G2: BUDGET 17 | H2: BUDGET 19 | I2: ORDINATO | J2: DA ORDINARE EXTRA | K2: TOTALE CON FORECAST | M2: =SUM(M5:M8) -> 1.0810977e+08
A3: 2 | B3: CIVIL WORKS | C3: =C16+C23+C29+C38+C64+C76+C80+C97+C107+C111+C133+C139+C143+C152+C156+C162 -> 112409767 | D3: =D16+D23+D29+D38+D64+D76+D80+D97+D107+D111+D133+D139+D143+D152+D156+D162 -> 1.1240977e+08 | E3: =E16+E23+E29+E38+E64+E76+E80+E97+E107+E111+E133+E139+E143+E152+E156+E162 -> 1.1240977e+08 | F3: =F16+F23+F29+F38+F64+F76+F80+F97+F107+F111+F133+F139+F143+F152+F156+F162 -> 1.0810977e+08 | G3: =G16+G23+G29+G38+G64+G76+G80+G97+G107+G111+G133+G139+G143+G152+G156+G162 -> 1.0810977e+08 | H3: =H16+H23+H29+H38+H64+H76+H80+H97+H107+H111+H133+H139+H143+H152+H156+H162 -> 1.0810977e+08 | I3: =I16+I23+I29+I38+I64+I76+I80+I97+I107+I111+I133+I139+I143+I152+I156+I162 -> 0 | J3: =J16+J23+J29+J38+J64+J76+J80+J97+J107+J111+J133+J139+J143+J152+J156+J162 -> 0 | K3: =K16+K23+K29+K38+K64+K76+K80+K97+K107+K111+K133+K139+K143+K152+K156+K162 -> 1.0810977e+08
G4: =G3-$F$3 -> 0.0033721477 | H4: =H3-$F$3 -> 0.0055060089 | K4: =K3-$F$3 -> 0.0055060089
L5: Ordered | M5: =H13+H14+H15+H20+H21+H27+H28+H34+H35+H36+H37+H44+H45+H47+H49+H50+H54+H57+H59+H60+H61+H70+H72+H75+H121++H123+H150+H149+H69 -> 53496524 | N5: =G15+G20+G21+G22+G27+G34+G35+G36+G44+G47+G49+G50+G54+G57+G59+G60+G61+G69+G70+G72+G75+G121+G123+G149+G150 -> 53701520
L6: Negotiation + buffer | M6: =H12+H33+H42+H43+H46+H48+H53+H56+H68+H71+H74+H120+H122+H148+H22 -> 16378807
D7: SAVINGS | J7: SAVINGS | L7: Planned | M7: =H26+H32+H62+H63+H55+H73+H79+H84+H85+H86+H87+H88+H89+H90+H91+H92+H93+H94+H95+H96+H102+H101+H103+H104+H105+H106+H110+H115+H116+H117+H118+H119+H124+H125+H126+H127+H128+H129+H130+H131+H132+H137+H138+H142+G1445+H151+H155+H160+H161+H147 -> 38234436
D8: EXTRA | J8: EXTRA | L8: Extra | M8: =SUM(I3:J3) -> 0
L9: (Buffer) | M9: =H42+H43+H46+H53+H120+H12+H33+H48+H56+H122+H68+H71+H74+H148+H22 -> 16378807
A11: 2.1 | B11: Foundation works | C11: 4613087 | D11: 0 | E11: 0 | F11: 0 | G11: 0 | H11: 0 | K11: =SUM(H11:J11) -> 0
A12: 2.1.1 | B12: Buffer | C12: 0 | D12: 1113087 | E12: 313087 | F12: 229887 | G12: 229887 | H12: 229887 | K12: =SUM(H12:J12) -> 229887
A13: 2.1.2 | B13: Diaphragm wall and barrettes part 1 | C13: 0 | D13: 3500000 | E13: 3176000 | F13: 0 | G13: 0 | H13: 0 | K13: =SUM(H13:J13) -> 0 | L13: Stump-Franki Sp. z o.o.
A14: 2.1.3 | B14: Barrettes part 2 | C14: 0 | D14: 0 | E14: 1124000 | F14: 0 | G14: 0 | H14: 0 | K14: =SUM(H14:J14) -> 0 | L14: Stump-Franki Sp. z o.o.
A15: 2.1.4 | B15: Concrete rubble ECD 45 | C15: 0 | D15: 0 | E15: 0 | F15: 83200 | G15: 83200 | H15: 83200 | K15: =SUM(H15:J15) -> 83200 | L15: Usługi Sprzętowo - Transportowe Sławomir Boruczkowski
C16: =SUM(C11:C15) -> 4613087 | D16: =SUM(D11:D15) -> 4613087 | E16: =SUM(E11:E15) -> 4613087 | F16: =SUM(F11:F15) -> 313087 | G16: =SUM(G11:G15) -> 313087 | H16: =SUM(H11:H15) -> 313087 | I16: =SUM(I11:I15) -> 0 | J16: =SUM(J11:J15) -> 0 | K16: =SUM(K11:K15) -> 313087
G17: =$F16-G16 -> 0 | H17: =$F16-H16 -> 0 | K17: =$F16-K16 -> 0
A19: 2.2 | B19: Earthworks | C19: 0 | D19: 0 | E19: 0 | F19: 0 | G19: 0 | H19: 0 | K19: =SUM(H19:J19) -> 0
A20: 2.2.1 | B20: ECR 3 / ECR 3 rev 1 working platform | C20: 176673 | D20: 176673 | E20: 176673 | F20: 176673 | G20: 176673 | H20: 176673 | K20: =SUM(H20:J20) -> 176673 | L20: MAR-KOP Marcin Mierzwa | M20: 4502939064
A21: 2.2.2 | B21: Earthmoving robots ECR 3 / ECR 3 rev 1 | C21: 2196542 | D21: 2196542 | E21: 2196542 | F21: 2196542 | G21: 2196542 | H21: 2196542 | K21: =SUM(H21:J21) -> 2196542 | L21: MAR-KOP Marcin Mierzwa | M21: 4502939064
A22: 2.2.3 | B22: Earthworks - backfill of retaining wall ECR 3 / ECR rev 1 | C22: 313419 | D22: 313419 | E22: 313419 | F22: 313419 | G22: 313419 | H22: 313419 | K22: =SUM(H22:J22) -> 313419
C23: =SUM(C19:C22) -> 2686634 | D23: =SUM(D19:D22) -> 2686634 | E23: =SUM(E19:E22) -> 2686634 | F23: =SUM(F19:F22) -> 2686634 | G23: =SUM(G19:G22) -> 2686634 | H23: =SUM(H19:H22) -> 2686634 | I23: =SUM(I19:I22) -> 0 | J23: =SUM(J19:J22) -> 0 | K23: =SUM(K19:K22) -> 2686634
G24: =$F23-G23 -> 0 | H24: =$F23-H23 -> 0 | K24: =$F23-K23 -> 0
A26: 2.3 | B26: Drainage | C26: 437599 | D26: 437599 | E26: 437599 | F26: 437599 | G26: 367599 | H26: 332599 | K26: =SUM(H26:J26) -> 332599
A27: 2.3.1 | B27: Dehydration ECD 50 | C27: 0 | D27: 0 | E27: 0 | F27: 0 | G27: 70000 | H27: 70000 | K27: =SUM(H27:J27) -> 70000 | L27: HAMER | M27: 4503066286
A28: 2.3.1 | B28: Dehydration ECD 50 rev 1 | C28: 0 | D28: 0 | E28: 0 | F28: 0 | G28: 0 | H28: 35000 | K28: =SUM(H28:J28) -> 35000 | L28: HAMER | M28: 4503066286
C29: =SUM(C26:C28) -> 437599 | D29: =SUM(D26:D28) -> 437599 | E29: =SUM(E26:E28) -> 437599 | F29: =SUM(F26:F28) -> 437599 | G29: =SUM(G26:G28) -> 437599 | H29: =SUM(H26:H28) -> 437599 | I29: =SUM(I26:I28) -> 0 | J29: =SUM(J26:J28) -> 0 | K29: =SUM(K26:K28) -> 437599
G30: =$F29-G29 -> -0.0028571429 | H30: =$F29-H29 -> -0.0028571429 | K30: =$F29-K29 -> -0.0028571429
A32: 2.4 | B32: Insulation | C32: 1138973 | D32: 1138973 | E32: 1138973 | F32: 403973 | G32: 345021 | H32: 298038 | K32: =SUM(H32:J32) -> 298038
A33: 2.4.1 | C33: 0 | D33: 0 | E33: 0 | F33: 1953.86 | G33: 1953.85 | H33: 1953.85 | K33: =SUM(H33:J33) -> 1953.85
A34: 2.4.1 | B34: ECR 11 reinforced concrete works | C34: 0 | D34: 0 | E34: 0 | F34: 733046.15 | G34: 733046.15 | H34: 733046.15 | K34: =SUM(H34:J34) -> 733046.15 | L34: AF KONSTRUKCJE | M34: 4502997466
A35: 2.4.2 | B35: Waterproofing ECD 51 | C35: 0 | D35: 0 | E35: 0 | F35: 0 | G35: 31352 | H35: 31352 | K35: =SUM(H35:J35) -> 31352 | L35: TWS | M35: 4503071267
A36: 2.4.3 | B36: Foundation insulation materials ECD 14 rev 3 | C36: 0 | D36: 0 | E36: 0 | F36: 0 | G36: 27600 | H36: 27600 | K36: =SUM(H36:J36) -> 27600 | L36: MAT-BUD | M36: 4502934293
A37: 2.4.4 | B37: Waterproofing - ECD 51 rev 1 | C37: 0 | D37: 0 | E37: 0 | F37: 0 | G37: 0 | H37: 46983 | K37: =SUM(H37:J37) -> 46983 | L37: TWS | M37: 4503071267
C38: =SUM(C32:C37) -> 1138973 | D38: =SUM(D32:D37) -> 1138973 | E38: =SUM(E32:E37) -> 1138973 | F38: =SUM(F32:F37) -> 1138973 | G38: =SUM(G32:G37) -> 1138973 | H38: =SUM(H32:H37) -> 1138973 | I38: =SUM(I32:I37) -> 0 | J38: =SUM(J32:J37) -> 0 | K38: =SUM(K32:K37) -> 1138973
G39: =$F38-G38 -> 0.01 | H39: =$F38-H38 -> 0.01 | K39: =$F38-K38 -> 0.01
A41: 2.5 | B41: Reinforced concrete structure | C41: 0 | D41: 0 | E41: 0 | F41: 0 | G41: 0 | H41: 0 | K41: =SUM(H41:J41) -> 0
A42: 2.5.1 | B42: Reinforced concrete foundation structure | C42: 16024473 | D42: 14169473 | E42: 10617413 | F42: 5117413.3 | G42: 5117413.3 | H42: 5117413.3 | K42: =SUM(H42:J42) -> 5117413.3
A43: 2.5.1.1 | B43: Supply of reinforcing steel | C43: 0 | D43: 33680.7 | E43: 33680.7 | F43: 33680.7 | G43: 33680.7 | H43: 7240.7 | K43: =SUM(H43:J43) -> 7240.7
A44: 2.5.1.1.1 | B44: Supply of ECR 2 reinforcing steel | C44: 0 | D44: 1821319 | E44: 1821319 | F44: 1821319 | G44: 1821319 | H44: 1821319 | K44: =SUM(H44:J44) -> 1821319 | L44: THYSSENKRUPP MATERIALS POLAND S.A. | M44: 4502938804
A45: 2.5.1.1.2 | B45: Reinforced meches - ECD 14 rev 4 | C45: 0 | D45: 0 | E45: 0 | F45: 0 | G45: 0 | H45: 26440 | K45: =SUM(H45:J45) -> 26440 | L45: MAT-BUD | M45: 4502934293
A46: 2.5.1.1.2 | B46: Concrete testing | C46: 0 | D46: 0 | E46: 500 | F46: 500 | G46: 500 | H46: 500 | K46: =SUM(H46:J46) -> 500
A47: 2.5.1.1.2 | B47: Concrete testing - ECD 31 | C47: 0 | D47: 0 | E47: 131560 | F47: 131560 | G47: 131560 | H47: 131560 | K47: =SUM(H47:J47) -> 131560 | L47: BARG | M47: 4502968920
A48: 2.5.1.1.3 | B48: Reinforced concrete works | C48: 0 | D48: 0 | E48: 0 | F48: 223042 | G48: 223042 | H48: 223042 | K48: =SUM(H48:J48) -> 223042
A49: 2.5.1.1.4 | C49: 0 | D49: 0 | E49: 0 | F49: 5276958 | G49: 5276958 | H49: 5276958 | K49: =SUM(H49:J49) -> 5276958 | L49: AF KONSTRUKCJE
A50: 2.5.1.2 | B50: Delivery of concrete mix including pumping service ECR 9 rev 1 / ECR 12 | C50: 0 | D50: 0 | E50: 3420000 | F50: 3420000 | G50: 3420000 | H50: 3420000 | K50: =SUM(H50:J50) -> 3420000 | L50: BUSZREM / HOLCIM | M50: 4502986603
A51: 2.5.1.3 | B51: Construction of reinforced concrete foundations and underground structures | C51: 0 | D51: 0 | E51: 0 | F51: 0 | G51: 0 | H51: 0 | K51: =SUM(H51:J51) -> 0
A52: 2.5.2 | B52: Reinforced concrete structure of the above-ground part, including prefabricated elements | C52: 0 | D52: 0 | E52: 0 | F52: 0 | G52: 0 | H52: 0 | K52: =SUM(H52:J52) -> 0
A53: 2.5.2.1 | B53: Reinforced concrete structure of the above-ground part of the B1 building - delivery and assembly of prefabricated elements | C53: 18708794 | D53: 8794 | E53: 8794 | F53: 0 | G53: 0 | H53: 0 | K53: =SUM(H53:J53) -> 0
A54: 2.5.2.1.1 | B54: Reinforced concrete structure of the above-ground part of the B1 facility - delivery and assembly of ECR 10 prefabricated elements | C54: 0 | D54: 18700000 | E54: 18700000 | F54: 18708794 | G54: 18708794 | H54: 18708794 | K54: =SUM(H54:J54) -> 18708794 | L54: BETARD
A55: 2.5.2.2 | B55: Reinforced concrete structure of the above-ground part of other buildings, including prefabricated elements | C55: 3426648 | D55: 1794248 | E55: 1794248 | F55: 990112 | G55: 990112 | H55: 990112 | K55: =SUM(H55:J55) -> 990112
A56: 2.5.2.2.1 | B56: Reinforced concrete works | C56: 0 | D56: 0 | E56: 0 | F56: 41927 | G56: 41927 | H56: 41927 | K56: =SUM(H56:J56) -> 41927
A57: 2.5.2.2.2 | B57: ECR 11 reinforced concrete works | C57: 0 | D57: 0 | E57: 0 | F57: 708073 | G57: 708073 | H57: 708073 | K57: =SUM(H57:J57) -> 708073 | L57: AF KONSTRUKCJE
A58: 2.5.2.3 | B58: Supply of reinforcing steel | C58: 0 | D58: 29639.15 | E58: 0 | F58: 0 | G58: 0 | H58: 0 | K58: =SUM(H58:J58) -> 0
A59: 2.5.2.3.1 | B59: Supply of ECR 2 reinforcing steel | C59: 0 | D59: 1602761 | E59: 1602761 | F59: 1602761 | G59: 1602761 | H59: 1602761 | K59: =SUM(H59:J59) -> 1602761 | L59: THYSSENKRUPP MATERIALS POLAND S.A. | M59: 4502938804
A60: 2.5.2.4 | B60: Delivery of concrete mix including pumping service ECR 9 rev 1 / ECR 12 | C60: 0 | D60: 0 | E60: 29639 | F60: 29639 | G60: 29639 | H60: 29639 | K60: =SUM(H60:J60) -> 29639 | L60: BUSZREM / HOLCIM | M60: 4502986603
A61: 2.5.4.4.1 | B61: Delivery of concrete mix with ECR 12 pumping service | C61: 0 | D61: 0 | E61: 0 | F61: 54136 | G61: 54136 | H61: 54136 | K61: =SUM(H61:J61) -> 54136 | L61: BUSZREM / HOLCIM
A62: 2.5.2.5 | B62: Flyover for belt conveyor | C62: 386500 | D62: 386500 | E62: 386500 | F62: 386500 | G62: 386500 | H62: 386500 | K62: =SUM(H62:J62) -> 386500
A63: 2.5.2.6 | B63: Retaining wall | C63: 718448 | D63: 718448 | E63: 718448 | F63: 718448 | G63: 718448 | H63: 718448 | K63: =SUM(H63:J63) -> 718448
C64: =SUM(C41:C63) -> 39264863 | D64: =SUM(D41:D63) -> 39264863 | E64: =SUM(E41:E63) -> 39264863 | F64: =SUM(F41:F63) -> 39264863 | G64: =SUM(G41:G63) -> 39264863 | H64: =SUM(H41:H63) -> 39264863 | I64: =SUM(I41:I63) -> 0 | J64: =SUM(J41:J63) -> 0 | K64: =SUM(K41:K63) -> 39264863
G65: =$F64-G64 -> -0.0060625598 | H65: =$F64-H64 -> -0.00087737292 | K65: =$F64-K64 -> -0.00087737292
A67: 2.6 | B67: Steel structures | C67: 0 | D67: 0 | E67: 0 | F67: 0 | G67: 0 | H67: 0 | K67: =SUM(H67:J67) -> 0
A68: 2.6.1 | B68: Structure, including platforms, walkways, ladders, roofing | C68: 23700876 | D68: 23700876 | E68: 23700876 | F68: 21982670 | G68: 7982670 | H68: 7982670 | K68: =SUM(H68:J68) -> 7982670
A69: 2.6.1.1 | B69: Detailed Design: Boiler Steel Support Structure and ECD 41 Equipment Support Structures | C69: 0 | D69: 0 | E69: 0 | F69: 443000 | G69: 443000 | H69: 443000.01 | K69: =SUM(H69:J69) -> 443000.01 | L69: ODS
A70: 2.6.1.2 | B70: Reinforced concrete structure of the above-ground part of the B1 facility - delivery and assembly of ECR 10 prefabricated elements | C70: 0 | D70: 0 | E70: 0 | F70: 1275206 | G70: 1275206 | H70: 1275206 | K70: =SUM(H70:J70) -> 1275206 | L70: BETARD
A71: 2.6.1.3 | B71: Structure, including platforms, platforms, ladders, canopies | C71: 0 | D71: 0 | E71: 0 | F71: 0 | G71: 953352 | H71: 953352 | K71: =SUM(H71:J71) -> 953352
A72: 2.6.1.3 | B72: Structure, including platforms, walkways, ladders, roofing | C72: 0 | D72: 0 | E72: 0 | F72: 0 | G72: 13046648 | H72: 13046648 | K72: =SUM(H72:J72) -> 13046648 | L72: NOWOSTAL
A73: 2.6.2 | B73: Steel structure of the staircase in the B1.4 facility (change from the reinforced concrete structure in relation to the acquisition stage) | C73: 470146 | D73: 470146 | E73: 470146 | F73: 470146 | G73: 470146 | H73: 470146 | K73: =SUM(H73:J73) -> 470146
A74: 2.6.3 | B74: Gantry beams | C74: 425469 | D74: 425469 | E74: 425469 | F74: 425469 | G74: 44669 | H74: 44669 | K74: =SUM(H74:J74) -> 44669
A75: 2.6.3.1 | C75: 0 | D75: 0 | E75: 0 | F75: 0 | G75: 380800 | H75: 380800 | K75: =SUM(H75:J75) -> 380800 | L75: NOWOSTAL
C76: =SUM(C67:C75) -> 24596491 | D76: =SUM(D67:D75) -> 24596491 | E76: =SUM(E67:E75) -> 24596491 | F76: =SUM(F67:F75) -> 24596491 | G76: =SUM(G67:G75) -> 24596491 | H76: =SUM(H67:H75) -> 24596491 | I76: =SUM(I67:I75) -> 0 | J76: =SUM(J67:J75) -> 0 | K76: =SUM(K67:K75) -> 24596491
G77: =$F76-G76 -> -0.0044524483 | H77: =$F76-H76 -> -0.011771493 | K77: =$F76-K76 -> -0.011771493
A79: 2.7 | B79: Brick walls | C79: 687451 | D79: 687451 | E79: 687451 | F79: 687451 | G79: 687451 | H79: 687451 | K79: =SUM(H79:J79) -> 687451
C80: =SUM(C79:C79) -> 687451 | D80: =SUM(D79:D79) -> 687451 | E80: =SUM(E79:E79) -> 687451 | F80: =SUM(F79:F79) -> 687451 | G80: =SUM(G79:G79) -> 687451 | H80: =SUM(H79:H79) -> 687451 | I80: =SUM(I79:I79) -> 0 | J80: =SUM(J79:J79) -> 0 | K80: =SUM(K79:K79) -> 687451
G81: =$F80-G80 -> 0 | H81: =$F80-H80 -> 0 | K81: =$F80-K80 -> 0
A83: 2.8 | B83: Facades | C83: 0 | D83: 0 | E83: 0 | F83: 0 | G83: 0 | H83: 0 | K83: =SUM(H83:J83) -> 0
A84: 2.8.1 | B84: Parapet | C84: 82476 | D84: 82476 | E84: 82476 | F84: 82476 | G84: 82476 | H84: 82476 | K84: =SUM(H84:J84) -> 82476
A85: 2.8.2 | B85: Steel-aluminum canopy | C85: 120923 | D85: 120923 | E85: 120923 | F85: 120923 | G85: 120923 | H85: 120923 | K85: =SUM(H85:J85) -> 120923
A86: 2.8.3 | B86: Aluminum-glass facade | C86: 296487 | D86: 296487 | E86: 296487 | F86: 296487 | G86: 296487 | H86: 296487 | K86: =SUM(H86:J86) -> 296487
A87: 2.8.4 | B87: ETICS | C87: 122038 | D87: 122038 | E87: 122038 | F87: 122038 | G87: 122038 | H87: 122038 | K87: =SUM(H87:J87) -> 122038
A88: 2.8.5 | B88: Flashings | C88: 366599 | D88: 366599 | E88: 366599 | F88: 366599 | G88: 366599 | H88: 366599 | K88: =SUM(H88:J88) -> 366599
A89: 2.8.6 | B89: Sheet metal cladding | C89: 1172887 | D89: 1172887 | E89: 1172887 | F89: 1172887 | G89: 1172887 | H89: 1172887 | K89: =SUM(H89:J89) -> 1172887
A90: 2.8.7 | B90: Sandwich panel cladding | C90: 5792280 | D90: 5792280 | E90: 5792280 | F90: 5792280 | G90: 5792280 | H90: 5792280 | K90: =SUM(H90:J90) -> 5792280
A91: 2.8.8 | B91: Fiber cement panel cladding | C91: 241171 | D91: 241171 | E91: 241171 | F91: 241171 | G91: 241171 | H91: 241171 | K91: =SUM(H91:J91) -> 241171
A92: 2.8.9 | B92: Substructures | C92: 419580 | D92: 419580 | E92: 419580 | F92: 419580 | G92: 419580 | H92: 419580 | K92: =SUM(H92:J92) -> 419580
A93: 2.8.10 | B93: Soffit lining | C93: 308662 | D93: 308662 | E93: 308662 | F93: 308662 | G93: 308662 | H93: 308662 | K93: =SUM(H93:J93) -> 308662
A94: 2.8.11 | B94: Scaffolding | C94: 77076 | D94: 77076 | E94: 77076 | F94: 77076 | G94: 77076 | H94: 77076 | K94: =SUM(H94:J94) -> 77076
... A96: 2.8.13 | B96: Shutters | C96: 107601 | D96: 107601 | E96: 107601 | F96: 107601 | G96: 107601 | H96: 107601 | K96: =SUM(H96:J96) -> 107601
C97: =SUM(C83:C96) -> 9257798 | D97: =SUM(D83:D96) -> 9257798 | E97: =SUM(E83:E96) -> 9257798 | F97: =SUM(F83:F96) -> 9257798 | G97: =SUM(G83:G96) -> 9257798 | H97: =SUM(H83:H96) -> 9257798 | I97: =SUM(I83:I96) -> 0 | J97: =SUM(J83:J96) -> 0 | K97: =SUM(K83:K96) -> 9257798
G98: =$F97-G97 -> 0 | H98: =$F97-H97 -> 0 | K98: =$F97-K97 -> 0
A100: 2.9 | B100: Doors, windows, gates and hatches | C100: 0 | D100: 0 | E100: 0 | F100: 0 | G100: 0 | H100: 0 | K100: =SUM(H100:J100) -> 0
A101: 2.9.1 | B101: Gates | C101: 1169929 | D101: 1169929 | E101: 1169929 | F101: 1169929 | G101: 1169929 | H101: 1169929 | K101: =SUM(H101:J101) -> 1169929
A102: 2.9.2 | B102: Interior doors | C102: 433042 | D102: 433042 | E102: 433042 | F102: 433042 | G102: 433042 | H102: 433042 | K102: =SUM(H102:J102) -> 433042
A103: 2.9.3 | B103: Exterior doors | C103: 164459 | D103: 164459 | E103: 164459 | F103: 164459 | G103: 164459 | H103: 164459 | K103: =SUM(H103:J103) -> 164459
A104: 2.9.4 | B104: Windows | C104: 366536 | D104: 366536 | E104: 366536 | F104: 366536 | G104: 366536 | H104: 366536 | K104: =SUM(H104:J104) -> 366536
A105: 2.9.5 | B105: Bunker windows | C105: 205428 | D105: 205428 | E105: 205428 | F105: 205428 | G105: 205428 | H105: 205428 | K105: =SUM(H105:J105) -> 205428
A106: 2.9.6 | B106: Hatches | C106: 327191 | D106: 327191 | E106: 327191 | F106: 327191 | G106: 327191 | H106: 327191 | K106: =SUM(H106:J106) -> 327191
C107: =SUM(C100:C106) -> 2666585 | D107: =SUM(D100:D106) -> 2666585 | E107: =SUM(E100:E106) -> 2666585 | F107: =SUM(F100:F106) -> 2666585 | G107: =SUM(G100:G106) -> 2666585 | H107: =SUM(H100:H106) -> 2666585 | I107: =SUM(I100:I106) -> 0 | J107: =SUM(J100:J106) -> 0 | K107: =SUM(K100:K106) -> 2666585
G108: =$F107-G107 -> 0 | H108: =$F107-H107 -> 0 | K108: =$F107-K107 -> 0
A110: 2.10 | B110: Roofs | C110: 7198646 | D110: 7198646 | E110: 7198646 | F110: 7198646 | G110: 7198646 | H110: 7198646 | K110: =SUM(H110:J110) -> 7198646
C111: =SUM(C110:C110) -> 7198646 | D111: =SUM(D110:D110) -> 7198646 | E111: =SUM(E110:E110) -> 7198646 | F111: =SUM(F110:F110) -> 7198646 | G111: =SUM(G110:G110) -> 7198646 | H111: =SUM(H110:H110) -> 7198646 | I111: =SUM(I110:I110) -> 0 | J111: =SUM(J110:J110) -> 0 | K111: =SUM(K110:K110) -> 7198646
G112: =$F111-G111 -> 0 | H112: =$F111-H111 -> 0 | K112: =$F111-K111 -> 0
...

Sheet 3_Electrical Works
C2: BUDGET APERTURA | D2: BUDGET 02 | E2: BUDGET 07 | F2: BUDGET 14 (B0 approvato Mar 26) | G2: BUDGET 17 | H2: BUDGET 19 | I2: ORDINATO | J2: DA ORDINARE EXTRA | K2: TOTALE CON FORECAST | M2: =SUM(M5:M8) -> 58345340
A3: 3 | B3: ELECTRICAL WORKS | C3: =C18+C23+C27+C35 -> 58345340 | D3: =D18+D23+D27+D35 -> 58345340 | E3: =E18+E23+E27+E35 -> 58345340 | F3: =F18+F23+F27+F35 -> 58345340 | G3: =G18+G23+G27+G35 -> 58345340 | H3: =H18+H23+H27+H35 -> 58345340 | I3: =I18+I23+I27+I35 -> 0 | J3: =J18+J23+J27+J35 -> 0 | K3: =K18+K23+K27+K35 -> 58345340
G4: =$F$3-G3 -> 0 | H4: =$F$3-H3 -> 0 | K4: =$F$3-K3 -> 0
L5: Ordered | M5: =H13+H22+H32 -> 36070000
L6: Negotiation + Buffer | M6: =H12+H31 -> 2016200
D7: SAVINGS | L7: Planned | M7: =H15+H14+H16+H17+H26+H33+H34 -> 20259140
D8: EXTRA | L8: Extra | M8: =SUM(I3:J3) -> 0
L9: (Buffer) | M9: =H12+H31 -> 2016200
A11: 3.1 | B11: Electrical installation | C11: 0 | D11: 0 | E11: 0 | F11: 0 | G11: 0 | H11: 0 | K11: =SUM(H11:J11) -> 0
A12: 3.1.1 | B12: Delivery and installation of electrical equipment | C12: 29982000 | D12: 29982000 | E12: 1700000 | F12: 1700000 | G12: 1700000 | H12: 1700000 | K12: =SUM(H12:J12) -> 1700000
A13: 3.1.1.1 | B13: Delivery and installation of electrical equipment | C13: 0 | D13: 0 | E13: 28282000 | F13: 28282000 | G13: 28282000 | H13: 28282000 | K13: =SUM(H13:J13) -> 28282000 | L13: ELEKTROSERV - ZAP | M13: ok
A14: 3.1.2 | B14: Electrical heat treacing of piping - hot part | C14: 742140 | D14: 742140 | E14: 742140 | F14: 742140 | G14: 742140 | H14: 742140 | K14: =SUM(H14:J14) -> 742140
A15: 3.1.3 | B15: Aviation warning lights | C15: 140000 | D15: 140000 | E15: 140000 | F15: 140000 | G15: 140000 | H15: 140000 | K15: =SUM(H15:J15) -> 140000
A16: 3.1.4 | B16: Fire detection and alarm system ( electrical&teletechnical part ) | C16: 980000 | D16: 980000 | E16: 980000 | F16: 980000 | G16: 980000 | H16: 980000 | K16: =SUM(H16:J16) -> 980000
A17: 3.1.5 | B17: Smoke extraction from waste bunker and tipping hall (electrical&teletechnical part ) | C17: 175000 | D17: 175000 | E17: 175000 | F17: 175000 | G17: 175000 | H17: 175000 | K17: =SUM(H17:J17) -> 175000
C18: =SUM(C11:C17) -> 32019140 | D18: =SUM(D11:D17) -> 32019140 | E18: =SUM(E11:E17) -> 32019140 | F18: =SUM(F11:F17) -> 32019140 | G18: =SUM(G11:G17) -> 32019140 | H18: =SUM(H11:H17) -> 32019140 | I18: =SUM(I11:I17) -> 0 | J18: =SUM(J11:J17) -> 0 | K18: =SUM(K11:K17) -> 32019140
G19: =$F18-G18 -> 0 | H19: =$F18-H18 -> 0 | K19: =$F18-K18 -> 0
A21: 3.2 | B21: Teletechnical installations | C21: 2579200 | D21: 0 | E21: 0 | F21: 0 | G21: 0 | H21: 0 | K21: =SUM(H21:J21) -> 0
A22: 3.2.1 | B22: Teletechnical installations | C22: 0 | D22: 2579200 | E22: 2579200 | F22: 2579200 | G22: 2579200 | H22: 2579200 | K22: =SUM(H22:J22) -> 2579200 | L22: ELEKTROSERV - ZAP | M22: ok
C23: =SUM(C21:C22) -> 2579200 | D23: =SUM(D21:D22) -> 2579200 | E23: =SUM(E21:E22) -> 2579200 | F23: =SUM(F21:F22) -> 2579200 | G23: =SUM(G21:G22) -> 2579200 | H23: =SUM(H21:H22) -> 2579200 | I23: =SUM(I21:I22) -> 0 | J23: =SUM(J21:J22) -> 0 | K23: =SUM(K21:K22) -> 2579200
G24: =$F23-G23 -> 0 | H24: =$F23-H23 -> 0 | K24: =$F23-K23 -> 0
A26: 3.3 | B26: GPO/GPZ power supply | C26: 13510000 | D26: 13510000 | E26: 13510000 | F26: 13510000 | G26: 13510000 | H26: 13510000 | K26: =SUM(H26:J26) -> 13510000
C27: =SUM(C26:C26) -> 13510000 | D27: =SUM(D26:D26) -> 13510000 | E27: =SUM(E26:E26) -> 13510000 | F27: =SUM(F26:F26) -> 13510000 | G27: =SUM(G26:G26) -> 13510000 | H27: =SUM(H26:H26) -> 13510000 | I27: =SUM(I26:I26) -> 0 | J27: =SUM(J26:J26) -> 0 | K27: =SUM(K26:K26) -> 13510000
G28: =$F27-G27 -> 0 | H28: =$F27-H27 -> 0 | K28: =$F27-K27 -> 0
A30: 3.3 | B30: I&C works | C30: 0 | D30: 0 | E30: 0 | F30: 0 | G30: 0 | H30: 0 | K30: =SUM(H30:J30) -> 0
A31: 3.4.1 | B31: Automation system and instrumentation, communication networks and control room devices | C31: 5525000 | D31: 686200 | E31: 316200 | F31: 316200 | G31: 316200 | H31: 316200 | K31: =SUM(H31:J31) -> 316200
A32: 3.4.1.1 | B32: Automation system and instrumentation, communication networks and control room devices | C32: 0 | D32: 4838800 | E32: 5208800 | F32: 5208800 | G32: 5208800 | H32: 5208800 | K32: =SUM(H32:J32) -> 5208800 | L32: ELEKTROSERV - ZAP | M32: ok
A33: 3.4.2 | B33: DCS System | C33: 2752000 | D33: 2752000 | E33: 2752000 | F33: 2752000 | G33: 2752000 | H33: 2752000 | K33: =SUM(H33:J33) -> 2752000
A34: 3.4.3 | B34: Emission monitoring system (CEMS) | C34: 1960000 | D34: 1960000 | E34: 1960000 | F34: 1960000 | G34: 1960000 | H34: 1960000 | K34: =SUM(H34:J34) -> 1960000
C35: =SUM(C30:C34) -> 10237000 | D35: =SUM(D30:D34) -> 10237000 | E35: =SUM(E30:E34) -> 10237000 | F35: =SUM(F30:F34) -> 10237000 | G35: =SUM(G30:G34) -> 10237000 | H35: =SUM(H30:H34) -> 10237000 | I35: =SUM(I30:I34) -> 0 | J35: =SUM(J30:J34) -> 0 | K35: =SUM(K30:K34) -> 10237000
G36: =$F35-G35 -> 0 | H36: =$F35-H35 -> 0 | K36: =$F35-K35 -> 0

Sheet 4_Sanitary works and FF
C2: BUDHET APERTURA | D2: BUDHET 02 | E2: BUDHET 07 | F2: BUDHET 14 (B0 approvato Mar 26) | G2: BUDGET 17 | H2: BUDGET 19 | I2: ORDINATO | J2: DA ORDINARE EXTRA | K2: TOTALE CON FORECAST | M2: =SUM(M6:M9) -> 21293319
A3: 4 | B3: SANITARY WORKS AND FIRE-FIHHTINH SYSTEM | C3: =C13+C27+C40 -> 21293319 | D3: =D13+D27+D40 -> 21293319 | E3: =E13+E27+E40 -> 21293319 | F3: =F13+F27+F40 -> 21293319 | G3: =H13+H27+H40 -> 21293319 | H3: =H13+H27+H40 -> 21293319 | I3: =I13+I27+I40 -> 0 | J3: =J13+J27+J40 -> 0 | K3: =K13+K27+K40 -> 21293319
G4: =$F$3-H3 -> 0 | H4: =$F$3-H3 -> 0 | K4: =$F$3-K3 -> 0
L6: Ordered | M6: 0
D7: SAVINH | J7: SAVINH | L7: NeHotiation | M7: =0 -> 0
D8: EXTRA | J8: EXTRA | L8: Planned | M8: =H12+H17+H18+H19+H20+H21+H22+H23+H24+H25+H26+H31+H32+H33+H34+H35+H36+H37+H38+H39 -> 21293319
K9: =K7+K8 -> 0 | L9: Extra | M9: 0
L10: (Buffer) | M10: 0
A12: 4.1 | B12: Deodorization system | C12: 1009700 | D12: 1009700 | E12: 1009700 | F12: 1009700 | G12: 1009700 | H12: 1009700 | K12: =SUM(H12:J12) -> 1009700
C13: =SUM(C12:C12) -> 1009700 | D13: =SUM(D12:D12) -> 1009700 | E13: =SUM(E12:E12) -> 1009700 | F13: =SUM(F12:F12) -> 1009700 | G13: =SUM(H12:H12) -> 1009700 | H13: =SUM(H12:H12) -> 1009700 | I13: =SUM(I12:I12) -> 0 | J13: =SUM(J12:J12) -> 0 | K13: =SUM(K12:K12) -> 1009700
G14: =$F13-H13 -> 0 | H14: =$F13-H13 -> 0 | K14: =$F13-K13 -> 0
A16: 4.2 | B16: FirefiHhtinH system | C16: 0 | D16: 0 | E16: 0 | F16: 0 | G16: 0 | H16: 0 | K16: =SUM(H16:J16) -> 0
A17: 4.2.1 | B17: Fire detection and alarm system | C17: 2211870 | D17: 2211870 | E17: 2211870 | F17: 2211870 | G17: 2211870 | H17: 2211870 | K17: =SUM(H17:J17) -> 2211870
A18: 4.2.2 | B18: FirefiHhtinH water tank | C18: 275700 | D18: 275700 | E18: 275700 | F18: 275700 | G18: 275700 | H18: 275700 | K18: =SUM(H18:J18) -> 275700
A19: 4.2.3 | B19: FirefiHhtinH water pumpinH | C19: 715920 | D19: 715920 | E19: 715920 | F19: 715920 | G19: 715920 | H19: 715920 | K19: =SUM(H19:J19) -> 715920
A20: 4.2.4 | B20: FirefiHhtinH water external distribution, hoses, sprinklers | C20: 821016 | D20: 821016 | E20: 821016 | F20: 821016 | G20: 821016 | H20: 821016 | K20: =SUM(H20:J20) -> 821016
A21: 4.2.5 | B21: Installation of internal hydrants in buildinHs B1 and B2 | C21: 240990 | D21: 240990 | E21: 240990 | F21: 240990 | G21: 240990 | H21: 240990 | K21: =SUM(H21:J21) -> 240990
A22: 4.2.6 | B22: Wireless radio controller system type WRC, Hun control | C22: 45500 | D22: 45500 | E22: 45500 | F22: 45500 | G22: 45500 | H22: 45500 | K22: =SUM(H22:J22) -> 45500
A23: 4.2.7 | B23: FirefiHhtinH water external distribution, hoses, sprinklers | C23: 542750 | D23: 542750 | E23: 542750 | F23: 542750 | G23: 542750 | H23: 542750 | K23: =SUM(H23:J23) -> 542750
A24: 4.2.8 | B24: Dry bunker sprinkler system. Installation of water and foam cannons in the bunker hall, and assembly of the valve sub-control unit. | C24: 1925350 | D24: 1925350 | E24: 1925350 | F24: 1925350 | G24: 1925350 | H24: 1925350 | K24: =SUM(H24:J24) -> 1925350
A25: 4.2.9 | B25: Natural Has (if any) and ammonia detection system | C25: 285000 | D25: 285000 | E25: 285000 | F25: 285000 | G25: 285000 | H25: 285000 | K25: =SUM(H25:J25) -> 285000
A26: 4.2.10 | B26: Smoke extraction from waste bunker and tippinH hall | C26: 1178293 | D26: 1178293 | E26: 1178293 | F26: 1178293 | G26: 1178293 | H26: 1178293 | K26: =SUM(H26:J26) -> 1178293
C27: =SUM(C16:C26) -> 8242389 | D27: =SUM(D16:D26) -> 8242389 | E27: =SUM(E16:E26) -> 8242389 | F27: =SUM(F16:F26) -> 8242389 | G27: =SUM(H16:H26) -> 8242389 | H27: =SUM(H16:H26) -> 8242389 | I27: =SUM(I16:I26) -> 0 | J27: =SUM(J16:J26) -> 0 | K27: =SUM(K16:K26) -> 8242389
G28: =$F27-H27 -> 0 | H28: =$F27-H27 -> 0 | K28: =$F27-K27 -> 0
A30: 4.3 | B30: Sanitary installations | C30: 0 | D30: 0 | E30: 0 | F30: 0 | G30: 0 | H30: 0 | K30: =SUM(H30:J30) -> 0
A31: 4.3.1 | B31: Boiler room roof ventilators and wall shutters | C31: 1500000 | D31: 1500000 | E31: 1500000 | F31: 1500000 | G31: 1500000 | H31: 1500000 | K31: =SUM(H31:J31) -> 1500000
A32: 4.3.2 | B32: HVAC for the technoloHical buildinHs | C32: 3107033 | D32: 3107033 | E32: 3107033 | F32: 3107033 | G32: 3107033 | H32: 3107033 | K32: =SUM(H32:J32) -> 3107033
A33: 4.3.3 | B33: HVAC for the other buildinHs | C33: 1548256 | D33: 1548256 | E33: 1548256 | F33: 1548256 | G33: 1548256 | H33: 1548256 | K33: =SUM(H33:J33) -> 1548256
A34: 4.3.4 | B34: Service water storaHe, pumpinH, underHround and external distribution + Sanitary facilities (toilets, showers, etc.) | C34: 1053444 | D34: 1053444 | E34: 1053444 | F34: 1053444 | G34: 1053444 | H34: 1053444 | K34: =SUM(H34:J34) -> 1053444
A35: 4.3.5 | B35: Sanitary water, connection to source, storaHe, pumpinH, underHround and external distribution | C35: 637613 | D35: 637613 | E35: 637613 | F35: 637613 | G35: 637613 | H35: 637613 | K35: =SUM(H35:J35) -> 637613
A36: 4.3.6 | B36: EmerHency showers and eye washers | C36: 10000 | D36: 10000 | E36: 10000 | F36: 10000 | G36: 10000 | H36: 10000 | K36: =SUM(H36:J36) -> 10000
A37: 4.3.7 | B37: Sanitary waste water collection, treatment and connection to discharHe point | C37: 624272 | D37: 624272 | E37: 624272 | F37: 624272 | G37: 624272 | H37: 624272 | K37: =SUM(H37:J37) -> 624272
A38: 4.3.8 | B38: Waste water collection and connection to discharHe point | C38: 200969 | D38: 200969 | E38: 200969 | F38: 200969 | G38: 200969 | H38: 200969 | K38: =SUM(H38:J38) -> 200969
A39: 4.3.9 | B39: Rain water and snowmelt collection, treatment and connection to discharHe point | C39: 3359643 | D39: 3359643 | E39: 3359643 | F39: 3359643 | G39: 3359643 | H39: 3359643 | K39: =SUM(H39:J39) -> 3359643
C40: =SUM(C30:C39) -> 12041230 | D40: =SUM(D30:D39) -> 12041230 | E40: =SUM(E30:E39) -> 12041230 | F40: =SUM(F30:F39) -> 12041230 | G40: =SUM(H30:H39) -> 12041230 | H40: =SUM(H30:H39) -> 12041230 | I40: =SUM(I30:I39) -> 0 | J40: =SUM(J30:J39) -> 0 | K40: =SUM(K30:K39) -> 12041230
G41: =$F40-H40 -> 0 | H41: =$F40-H40 -> 0 | K41: =$F40-K40 -> 0

Sheet 5_Mechanical and technological
C2: BUDGET APERTURA | D2: BUDGET 02 | E2: BUDGET 07 | F2: BUDGET 14 (B0 approvato Mar 26) | G2: BUDGET 17 | H2: BUDGET 19 | I2: ORDINATO | J2: DA ORDINARE EXTRA | K2: TOTALE CON FORECAST | M2: =SUM(M5:M8) -> 2.5866665e+08
A3: 5 | B3: MECHANICAL AND TECHNOLOGICAL WORKS | C3: =C13+C19+C31+C46+C50+C54+C62+C69+C73+C99+C104+C108+C122+C131 -> 258666646 | D3: =D13+D19+D31+D46+D50+D54+D62+D69+D73+D99+D104+D108+D122+D131 -> 2.5866665e+08 | E3: =E13+E19+E31+E46+E50+E54+E62+E69+E73+E99+E104+E108+E122+E131 -> 2.5866665e+08 | F3: =F13+F19+F31+F46+F50+F54+F62+F69+F73+F99+F104+F108+F122+F131 -> 2.5866665e+08 | G3: =G13+G19+G31+G46+G50+G54+G62+G69+G73+G99+G104+G108+G122+G131 -> 2.5866665e+08 | H3: =H13+H19+H31+H46+H50+H54+H62+H69+H73+H99+H104+H108+H122+H131 -> 2.5866665e+08 | I3: =I13+I19+I31+I46+I50+I54+I62+I69+I73+I99+I104+I108+I122+I131 -> 0 | J3: =J13+J19+J31+J46+J50+J54+J62+J69+J73+J99+J104+J108+J122+J131 -> 0 | K3: =K13+K19+K31+K46+K50+K54+K62+K69+K73+K99+K104+K108+K122+K131 -> 2.5866665e+08
G4: =$E$3-G3 -> 0.000395298 | H4: =$E$3-H3 -> -0.0041679144 | K4: =$E$3-K3 -> -0.0041679144
L5: Ordered | M5: =H23+H59+H36+H41+H80+H103+H127+H17+H24+H25+H38+H39+H40+H53+H67+H78+H83+H89 -> 1.5305376e+08
L6: Negotiation + buffer | M6: =H35+H79+H102+H126+H37+H66+H77+H82 -> 6615898
C7: SAVINGS | D7: 0 | E7: 0 | F7: 0 | G7: 0 | H7: 0 | J7: SAVINGS | K7: 0 | L7: Planned | M7: =H12+H18+H26+H27+H28+H29+H30+H42+H43+H44+H45+H49+H58+H60+H61+H68+H72+H81+H84+H85+H86+H87+H90+H91+H92+H94+H95+H96+H97+H98+H107+H112+H114+H113+H115+H116+H117+H118+H119+H120+H121+H128+H129+H130 -> 98996985
C8: EXTRA | D8: 0 | E8: 0 | F8: 0 | G8: 0 | H8: 0 | J8: EXTRA | K8: 0 | L8: Extra | M8: 0
L9: (Buffer) | M9: =H126+H102+H82+H79+H77+H37+H35+H66 -> 6615898
A11: 5.1 | B11: Reception | C11: 0 | D11: 0 | E11: 0 | F11: 0 | G11: 0 | H11: 0 | K11: =SUM(H11:J11) -> 0
A12: 5.1.1 | B12: Radioactivity detector | C12: 185000 | D12: 185000 | E12: 185000 | F12: 185000 | G12: 185000 | H12: 185000 | K12: =SUM(H12:J12) -> 185000
C13: =SUM(C11:C12) -> 185000 | D13: =SUM(D11:D12) -> 185000 | E13: =SUM(E11:E12) -> 185000 | F13: =SUM(F11:F12) -> 185000 | G13: =SUM(G11:G12) -> 185000 | H13: =SUM(H11:H12) -> 185000 | I13: =SUM(I11:I12) -> 0 | J13: =SUM(J11:J12) -> 0 | K13: =SUM(K11:K12) -> 185000
G14: =$F13-G13 -> 0 | H14: =$F13-H13 -> 0 | K14: =$F13-K13 -> 0
A16: 5.2 | B16: Waste bunker | C16: 0 | D16: 0 | E16: 0 | F16: 0 | G16: 0 | H16: 0 | K16: =SUM(H16:J16) -> 0
A17: 5.2.1 | B17: Overhead crane, grab and operator seat + Spare Grab - ECR 14 | C17: 9072785 | D17: 9072785 | E17: 9072785 | F17: 9072785 | G17: 9072785 | H17: 9072785 | K17: =SUM(H17:J17) -> 9072785 | L17: ZBUD | M17: 4503036767
A18: 5.2.2 | B18: Trapdoors for grab maintenance | C18: 81600 | D18: 81600 | E18: 81600 | F18: 81600 | G18: 81600 | H18: 81600 | K18: =SUM(H18:J18) -> 81600
C19: =SUM(C16:C18) -> 9154385 | D19: =SUM(D16:D18) -> 9154385 | E19: =SUM(E16:E18) -> 9154385 | F19: =SUM(F16:F18) -> 9154385 | G19: =SUM(G16:G18) -> 9154385 | H19: =SUM(H16:H18) -> 9154385 | I19: =SUM(I16:I18) -> 0 | J19: =SUM(J16:J18) -> 0 | K19: =SUM(K16:K18) -> 9154385
G20: =$F19-G19 -> 0 | H20: =$F19-H19 -> 0 | K20: =$F19-K19 -> 0
A22: 5.3 | B22: Furnace | C22: 0 | D22: 0 | E22: 0 | F22: 0 | G22: 0 | H22: 0 | K22: =SUM(H22:J22) -> 0
A23: 5.3.1 | B23: Furnace charging hopper + Furnace supporting steel structure + Complete grate fired furnace with waste feeding system + Hoppers under grate | C23: 33755000 | D23: 33755000 | E23: 33755000 | F23: 33755000 | G23: 33755000 | H23: 33755000 | K23: =SUM(H23:J23) -> 33755000 | L23: TM.E. S.p.A - Termomeccanica Ecologia
A24: 5.3.2 | B24: Primary and secondary air fan, Flue gas recirculation fan, ID Fan | C24: 595000 | D24: 595000 | E24: 595000 | F24: 595000 | G24: 595000 | H24: 595000 | K24: =SUM(H24:J24) -> 595000 | L24: OWENT | M24: 4503139940
A25: 5.3.3 | B25: Primary & secondary air heat exchanger | C25: 1281400 | D25: 1281400 | E25: 1281400 | F25: 1281400 | G25: 1281400 | H25: 1281400 | K25: =SUM(H25:J25) -> 1281400 | L25: AS TECHNOLOGIE | M25: 4503139820
A26: 5.3.4 | B26: Primary / secondary air ducts + Flue gas recirculation ducts + Auxiliary burners ducts + Supporting structures | C26: 2502500 | D26: 2502500 | E26: 2502500 | F26: 2502500 | G26: 2502500 | H26: 2502500 | K26: =SUM(H26:J26) -> 2502500
A27: 5.3.5 | B27: Fire curtain for primary air opening | C27: 100000 | D27: 100000 | E27: 100000 | F27: 100000 | G27: 100000 | H27: 100000 | K27: =SUM(H27:J27) -> 100000
A28: 5.3.6 | B28: Primary & secondary air dampers | C28: 220000 | D28: 220000 | E28: 220000 | F28: 220000 | G28: 220000 | H28: 220000 | K28: =SUM(H28:J28) -> 220000
A29: 5.3.7 | B29: Flue gas recirculation dampers | C29: 40000 | D29: 40000 | E29: 40000 | F29: 40000 | G29: 40000 | H29: 40000 | K29: =SUM(H29:J29) -> 40000
A30: 5.3.8 | B30: Camera for furnace monitoring | C30: 51600 | D30: 51600 | E30: 51600 | F30: 51600 | G30: 51600 | H30: 51600 | K30: =SUM(H30:J30) -> 51600
C31: =SUM(C22:C30) -> 38545500 | D31: =SUM(D22:D30) -> 38545500 | E31: =SUM(E22:E30) -> 38545500 | F31: =SUM(F22:F30) -> 38545500 | G31: =SUM(G22:G30) -> 38545500 | H31: =SUM(H22:H30) -> 38545500 | I31: =SUM(I22:I30) -> 0 | J31: =SUM(J22:J30) -> 0 | K31: =SUM(K22:K30) -> 38545500
G32: =$F31-G31 -> 0 | H32: =$F31-H31 -> 0.0033333376 | K32: =$F31-K31 -> 0.0033333376
A34: 5.4 | B34: Boiler | C34: 0 | D34: 0 | E34: 0 | F34: 0 | G34: 0 | H34: 0 | K34: =SUM(H34:J34) -> 0
A35: 5.4.1 | B35: Boiler - pressure parts | C35: 54332011 | D35: 54332011 | E35: 54332011 | F35: 54332011 | G35: 8342011 | H35: 4948411 | K35: =SUM(H35:J35) -> 4948411
A36: 5.4.1.1 | B36: Boiler - ECR 13 | C36: 0 | D36: 0 | E36: 0 | F36: 0 | G36: 45990000 | H36: 45990000 | K36: =SUM(H36:J36) -> 45990000 | L36: SEFAKO | M36: 4503036513
A37: 5.4.1.2 | B37: Burners including fans | C37: 0 | D37: 0 | E37: 0 | F37: 0 | G37: 0 | H37: 17900 | K37: =SUM(H37:J37) -> 17900
A38: 5.4.1.2 | B38: Burners including fans - ECR 21 | C38: 0 | D38: 0 | E38: 0 | F38: 0 | G38: 0 | H38: 492100 | K38: =SUM(H38:J38) -> 492100 | L38: BCE
A39: 5.4.1.3 | B39: Primary & secondary air heat exchanger - ECR 22 | C39: 0 | D39: 0 | E39: 0 | F39: 0 | G39: 0 | H39: 1118600 | K39: =SUM(H39:J39) -> 1118600 | L39: AS TECHNOLOGIE | M39: 4503139820
A40: 5.4.1.4 | B40: Primary and secondary air fan, Flue gas recirculation fan, ID Fan - ECR 23 | C40: 0 | D40: 0 | E40: 0 | F40: 0 | G40: 0 | H40: 1765000 | K40: =SUM(H40:J40) -> 1765000 | L40: OWENT | M40: 4503139940
A41: 5.4.2 | B41: Boiler - supporting structure including walkways - ECR 16 | C41: 6374147 | D41: 6374147 | E41: 6374147 | F41: 6374147 | G41: 6374147 | H41: 6374147 | K41: =SUM(H41:J41) -> 6374147 | L41: NOWOSTAL
A42: 5.4.3 | B42: Fly ash extraction system for the boiler and conveyors | C42: 4260000 | D42: 4260000 | E42: 4260000 | F42: 4260000 | G42: 4260000 | H42: 4260000 | K42: =SUM(H42:J42) -> 4260000
A43: 5.4.4 | B43: Sampling system | C43: 1010500 | D43: 1010500 | E43: 1010500 | F43: 1010500 | G43: 1010500 | H43: 1010500 | K43: =SUM(H43:J43) -> 1010500
A44: 5.4.5 | B44: Chemical dosing for the boiler | C44: 223600 | D44: 223600 | E44: 223600 | F44: 223600 | G44: 223600 | H44: 223600 | K44: =SUM(H44:J44) -> 223600
A45: 5.4.6 | B45: Compensator between boiler and ECO | C45: 129000 | D45: 129000 | E45: 129000 | F45: 129000 | G45: 129000 | H45: 129000 | K45: =SUM(H45:J45) -> 129000
C46: =SUM(C34:C45) -> 66329258 | D46: =SUM(D34:D45) -> 66329258 | E46: =SUM(E34:E45) -> 66329258 | F46: =SUM(F34:F45) -> 66329258 | G46: =SUM(G34:G45) -> 66329258 | H46: =SUM(H34:H45) -> 66329258 | I46: =SUM(I34:I45) -> 0 | J46: =SUM(J34:J45) -> 0 | K46: =SUM(K34:K45) -> 66329258
G47: =$F46-G46 -> 0 | H47: =$F46-H46 -> 0 | K47: =$F46-K46 -> 0
A49: 5.5 | B49: Refractory | C49: 3993000 | D49: 3993000 | E49: 3993000 | F49: 3993000 | G49: 3993000 | H49: 3993000 | K49: =SUM(H49:J49) -> 3993000
C50: =C49 -> 3993000 | D50: =D49 -> 3993000 | E50: =E49 -> 3993000 | F50: =F49 -> 3993000 | G50: =G49 -> 3993000 | H50: =H49 -> 3993000 | I50: =I49 -> 0 | J50: =J49 -> 0 | K50: =K49 -> 3993000
G51: =$F50-G50 -> 0 | H51: =$F50-H50 -> 0 | K51: =$F50-K50 -> 0
A53: 5.6 | B53: Burners including fans | C53: 1062800 | D53: 1062800 | E53: 1062800 | F53: 1062800 | G53: 1062800 | H53: 1062800 | K53: =SUM(H53:J53) -> 1062800 | L53: BCE
C54: =C53 -> 1062800 | D54: =D53 -> 1062800 | E54: =E53 -> 1062800 | F54: =F53 -> 1062800 | G54: =G53 -> 1062800 | H54: =H53 -> 1062800 | I54: =I53 -> 0 | J54: =J53 -> 0 | K54: =K53 -> 1062800
G55: =$F54-G54 -> 0 | H55: =$F54-H54 -> 0 | K55: =$F54-K54 -> 0
A57: 5.7 | B57: Flue gas treatment (FGT) | C57: 0 | D57: 0 | E57: 0 | F57: 0 | G57: 0 | H57: 0 | K57: =SUM(H57:J57) -> 0
A58: 5.7.1 | B58: SNCR DeNOx system including silo, pumps | C58: 1090000 | D58: 1090000 | E58: 1090000 | F58: 1090000 | G58: 1090000 | H58: 1090000 | K58: =SUM(H58:J58) -> 1090000
A59: 5.7.2 | B59: Flue gas treatment (FGT): Bag filter, Reactor, DeNOx, Flue gas condensation, Lime and activated carbon silos, dosing system | C59: 33755000 | D59: 33755000 | E59: 33755000 | F59: 33755000 | G59: 33755000 | H59: 33755000 | K59: =SUM(H59:J59) -> 33755000 | L59: TM.E. S.p.A - Termomeccanica Ecologia
A60: 5.7.3 | B60: Bag filters delivery | C60: 400000 | D60: 400000 | E60: 400000 | F60: 400000 | G60: 400000 | H60: 400000 | K60: =SUM(H60:J60) -> 400000
A61: 5.7.4 | B61: Fly ash silos | C61: 2000000 | D61: 2000000 | E61: 2000000 | F61: 2000000 | G61: 2000000 | H61: 2000000 | K61: =SUM(H61:J61) -> 2000000
C62: =SUM(C57:C61) -> 37245000 | D62: =SUM(D57:D61) -> 37245000 | E62: =SUM(E57:E61) -> 37245000 | F62: =SUM(F57:F61) -> 37245000 | G62: =SUM(G57:G61) -> 37245000 | H62: =SUM(H57:H61) -> 37245000 | I62: =SUM(I57:I61) -> 0 | J62: =SUM(J57:J61) -> 0 | K62: =SUM(K57:K61) -> 37245000
G63: =$F62-G62 -> 0 | H63: =$F62-H62 -> 0 | K63: =$F62-K62 -> 0
A65: 5.8 | B65: Bottom ash extraction | C65: 0 | D65: 0 | E65: 0 | F65: 0 | G65: 0 | H65: 0 | K65: =SUM(H65:J65) -> 0
A66: 5.8.1 | B66: Chain conveyor under grate + Bottom ash extractor + Vibrating table / bulk screen | C66: 1567228 | D66: 1567228 | E66: 1567228 | F66: 1567228 | G66: 1567228 | H66: 118828 | K66: =SUM(H66:J66) -> 118828
A67: 5.8.1 | B67: Prefabrication, delivery, and commissioning of a system for removing bottom ash and slag ECR 17 | C67: 0 | D67: 0 | E67: 0 | F67: 0 | G67: 0 | H67: 1448400 | K67: =SUM(H67:J67) -> 1448400 | L67: LOIBL | M67: 4503106362
A68: 5.8.2 | B68: Belt conveyors | C68: 2347800 | D68: 2347800 | E68: 2347800 | F68: 2347800 | G68: 2347800 | H68: 2347800 | K68: =SUM(H68:J68) -> 2347800
C69: =SUM(C65:C68) -> 3915028 | D69: =SUM(D65:D68) -> 3915028 | E69: =SUM(E65:E68) -> 3915028 | F69: =SUM(F65:F68) -> 3915028 | G69: =SUM(G65:G68) -> 3915028 | H69: =SUM(H65:H68) -> 3915028 | I69: =SUM(I65:I68) -> 0 | J69: =SUM(J65:J68) -> 0 | K69: =SUM(K65:K68) -> 3915028
G70: =$F69-G69 -> 0 | H70: =$F69-H69 -> -9.999983e-05 | K70: =$F69-K69 -> -9.999983e-05
A72: 5.9 | B72: Bottom ash / slag valorization | C72: 8271000 | D72: 8271000 | E72: 8271000 | F72: 8271000 | G72: 8271000 | H72: 8271000 | K72: =SUM(H72:J72) -> 8271000
C73: =C72 -> 8271000 | D73: =D72 -> 8271000 | E73: =E72 -> 8271000 | F73: =F72 -> 8271000 | G73: =G72 -> 8271000 | H73: =H72 -> 8271000 | I73: =I72 -> 0 | J73: =J72 -> 0 | K73: =K72 -> 8271000
G74: =$F73-G73 -> 0 | H74: =$F73-H73 -> 0 | K74: =$F73-K73 -> 0
A76: 5.10 | B76: Steam turbine, thermal cycle & district heating network | C76: 0 | D76: 0 | E76: 0 | F76: 0 | G76: 0 | H76: 0 | K76: =SUM(H76:J76) -> 0
A77: 5.10.1 | B77: Steam turbine - gear box - generator. Including accessories: oil system, coolers, insulation, pipes and valves, control panel, protection panel, synchro system etc. | C77: 13374290 | D77: 13374290 | E77: 13374290 | F77: 13374290 | G77: 13374290 | H77: 394396 | K77: =SUM(H77:J77) -> 394396
A78: 5.10.1.1 | B78: Steam turbine - gear box - generator. Including accessories: oil system, coolers, insulation, pipes and valves, control panel, protection panel, synchro system etc. - ECR 19 | C78: 0 | D78: 0 | E78: 0 | F78: 0 | G78: 0 | H78: 12979894 | K78: =SUM(H78:J78) -> 12979894 | L78: TRIVIENI TURBINE | M78: 4503120533
A79: 5.10.2 | B79: Auxiliary crane and hoists for the maintenance of the steam turbine | C79: 300000 | D79: 300000 | E79: 300000 | F79: 300000 | G79: 222785 | H79: 222785 | K79: =SUM(H79:J79) -> 222785
A80: 5.10.2 | B80: Gripper service flaps - ECR 14 | C80: 0 | D80: 0 | E80: 0 | F80: 0 | G80: 77215 | H80: 77215 | K80: =SUM(H80:J80) -> 77215 | L80: ZBUD | M80: 4503036767
A81: 5.10.3 | B81: Air cooled condenser | C81: 9000000 | D81: 9000000 | E81: 9000000 | F81: 9000000 | G81: 9000000 | H81: 9000000 | K81: =SUM(H81:J81) -> 9000000
A82: 5.10.4 | B82: Feed water tank and Deaerator | C82: 1000000 | D82: 1000000 | E82: 1000000 | F82: 1000000 | G82: 1000000 | H82: 267260 | K82: =SUM(H82:J82) -> 267260
A83: 5.10.4.1 | B83: Feed water tank and Deaerator ECR 18 | C83: 0 | D83: 0 | E83: 0 | F83: 0 | G83: 0 | H83: 732740 | K83: =SUM(H83:J83) -> 732740 | L83: ESTANC AS | M83: 4503121635
A84: 5.10.5 | B84: Piping, fitting and supports | C84: 18664194 | D84: 18664194 | E84: 18664194 | F84: 18664194 | G84: 18664194 | H84: 18664194 | K84: =SUM(H84:J84) -> 18664194
A85: 5.10.6 | B85: Chemical dossing for thermal cycle and district heating | C85: 550000 | D85: 550000 | E85: 550000 | F85: 550000 | G85: 550000 | H85: 550000 | K85: =SUM(H85:J85) -> 550000
A86: 5.10.7 | B86: Main cooler | C86: 2000000 | D86: 2000000 | E86: 2000000 | F86: 2000000 | G86: 2000000 | H86: 2000000 | K86: =SUM(H86:J86) -> 2000000
A87: 5.10.8 | B87: Cooler tank, condensate tank | C87: 1000000 | D87: 1000000 | E87: 1000000 | F87: 1000000 | G87: 1000000 | H87: 1000000 | K87: =SUM(H87:J87) -> 1000000
A88: 5.10.9 | B88: Water pressure stabilization system | C88: 350000 | D88: 350000 | E88: 350000 | F88: 350000 | G88: 350000 | H88: 0 | K88: =SUM(H88:J88) -> 0
A89: 5.10.9.1 | B89: Feed water tank and Deaerator ECR 18 | C89: 0 | D89: 0 | E89: 0 | F89: 0 | G89: 0 | H89: 350000 | K89: =SUM(H89:J89) -> 350000 | L89: ESTANC AS | M89: 4503121635
A90: 5.10.10 | B90: Water tank 100 m3 | C90: 200000 | D90: 200000 | E90: 200000 | F90: 200000 | G90: 200000 | H90: 200000 | K90: =SUM(H90:J90) -> 200000
A91: 5.10.11 | B91: Heat exchangers 2 pcs., LP pre-heater, external economizer | C91: 3242866 | D91: 3242866 | E91: 3242866 | F91: 3242866 | G91: 3242866 | H91: 3242866 | K91: =SUM(H91:J91) -> 3242866
A92: 5.10.12 | B92: Stabilising pumps 2 x 100%, network pumps 3 x 50%, condensate pumps 2 x 100%, feed water pumps 3 pcs., cooling pumps | C92: 5517325 | D92: 5517325 | E92: 5517325 | F92: 5517325 | G92: 5517325 | H92: 5517325 | K92: =SUM(H92:J92) -> 5517325
A93: 5.10.13 | B93: Valves ( Manual, motorized , safety, ON-OF , control etc… ) | C93: 0 | D93: 0 | E93: 0 | F93: 0 | G93: 0 | H93: 0 | K93: =SUM(H93:J93) -> 0
A94: 5.10.13.1 | B94: Manual valves | C94: 2200000 | D94: 2200000 | E94: 2200000 | F94: 2200000 | G94: 2200000 | H94: 2200000 | K94: =SUM(H94:J94) -> 2200000
A95: 5.10.13.2 | B95: Motorized valves | C95: 1000000 | D95: 1000000 | E95: 1000000 | F95: 1000000 | G95: 1000000 | H95: 1000000 | K95: =SUM(H95:J95) -> 1000000
A96: 5.10.13.3 | B96: Safety valves | C96: 200000 | D96: 200000 | E96: 200000 | F96: 200000 | G96: 200000 | H96: 200000 | K96: =SUM(H96:J96) -> 200000
A97: 5.10.13.4 | B97: ON/OFF valves | C97: 400000 | D97: 400000 | E97: 400000 | F97: 400000 | G97: 400000 | H97: 400000 | K97: =SUM(H97:J97) -> 400000
A98: 5.10.13.5 | B98: Control valves | C98: 700000 | D98: 700000 | E98: 700000 | F98: 700000 | G98: 700000 | H98: 700000 | K98: =SUM(H98:J98) -> 700000
C99: =SUM(C76:C98) -> 59698675 | D99: =SUM(D76:D98) -> 59698675 | E99: =SUM(E76:E98) -> 59698675 | F99: =SUM(F76:F98) -> 59698675 | G99: =SUM(G76:G98) -> 59698675 | H99: =SUM(H76:H98) -> 59698675 | I99: =SUM(I76:I98) -> 0 | J99: =SUM(J76:J98) -> 0 | K99: =SUM(K76:K98) -> 59698675
G100: =$F99-G99 -> 0 | H100: =$F99-H99 -> -0.00090000033 | K100: =$F99-K99 -> -0.00090000033
A102: 5.11 | B102: Stack | C102: 1850000 | D102: 1850000 | E102: 1850000 | F102: 1850000 | G102: 346317.95 | H102: 346317.95 | K102: =SUM(H102:J102) -> 346317.95
A103: 5.11.1 | B103: Stack - ECR 15 | C103: 0 | D103: 0 | E103: 0 | F103: 0 | G103: 1503682.1 | H103: 1503682.1 | K103: =SUM(H103:J103) -> 1503682.1 | L103: AVANTEA STEEL SOLUTIONS | M103: 4503064698
C104: =SUM(C102:C103) -> 1850000 | D104: =SUM(D102:D103) -> 1850000 | E104: =SUM(E102:E103) -> 1850000 | F104: =SUM(F102:F103) -> 1850000 | G104: =SUM(G102:G103) -> 1850000 | H104: =SUM(H102:H103) -> 1850000 | I104: =SUM(I102:I103) -> 0 | J104: =SUM(J102:J103) -> 0 | K104: =SUM(K102:K103) -> 1850000
G105: =$F104-G104 -> 0 | H105: =$F104-H104 -> 0 | K105: =$F104-K104 -> 0
A107: 5.12 | B107: Boiler and piping insulation | C107: 11000000 | D107: 11000000 | E107: 11000000 | F107: 11000000 | G107: 11000000 | H107: 11000000 | K107: =SUM(H107:J107) -> 11000000
C108: =C107 -> 11000000 | D108: =D107 -> 11000000 | E108: =E107 -> 11000000 | F108: =F107 -> 11000000 | G108: =G107 -> 11000000 | H108: =H107 -> 11000000 | I108: =I107 -> 0 | J108: =J107 -> 0 | K108: =K107 -> 11000000
G109: =$F108-G108 -> 0 | H109: =$F108-H108 -> 0 | K109: =$F108-K108 -> 0
A111: 5.13 | B111: Ancillary systems | C111: 0 | D111: 0 | E111: 0 | F111: 0 | G111: 0 | H111: 0 | K111: =SUM(H111:J111) -> 0
A112: 5.13.1 | B112: Compressors 2 x 50% + 1 x 50% | C112: 1500000 | D112: 1500000 | E112: 1500000 | F112: 1500000 | G112: 1500000 | H112: 1500000 | K112: =SUM(H112:J112) -> 1500000
A113: 5.13.2 | B113: Auxiliary fuel tank (light oil/diesel oil) | C113: 200000 | D113: 200000 | E113: 200000 | F113: 200000 | G113: 200000 | H113: 200000 | K113: =SUM(H113:J113) -> 200000
A114: 5.13.3 | B114: Light oil unloading installation with TDT documentation approval | C114: 200000 | D114: 200000 | E114: 200000 | F114: 200000 | G114: 200000 | H114: 200000 | K114: =SUM(H114:J114) -> 200000
...

Sheet 6_ Commissioning
C2: BUDGET APERTURA | D2: BUDGET 02 | E2: BUDGET 07 | F2: BUDGET 14 (B0 approvato Mar 26) | G2: BUDGET 17 | H2: BUDGET 19 | I2: ORDINATO EXTRA | J2: DA ORDINARE EXTRA | K2: TOTALE CON FORECAST | M2: =SUM(M5:M8) -> 8500000
A3: 6 | B3: COLD AND HOT COMMISSIONING & TRIAL RUN OF TECHNOLOGICAL EQUIPMENT | C3: =C16+C27+C31+C36+C40+C44 -> 8500000 | D3: =D16+D27+D31+D36+D40+D44 -> 8500000 | E3: =E16+E27+E31+E36+E40+E44 -> 8500000 | F3: =F16+F27+F31+F36+F40+F44 -> 8500000 | G3: =G16+G27+G31+G36+G40+G44 -> 8500000 | H3: =H16+H27+H31+H36+H40+H44 -> 8500000 | I3: =I16+I27+I31+I36+I40+I44 -> 0 | J3: =J16+J27+J31+J36+J40+J44 -> 0 | K3: =K16+K27+K31+K36+K40+K44 -> 8500000
H4: =$F$3-H3 -> 0 | K4: =$F$3-K3 -> 0
L5: Ordered | M5: =H35 -> 100000
L6: Negotiation + buffer | M6: =H34 -> 400000
D7: SAVINGS | J7: SAVINGS | L7: Planned | M7: =H12+H13+H14+H15+H20+H21+H22+H23+H24+H26+H25+H30+H39+H43 -> 8000000
D8: EXTRA | J8: EXTRA | L8: Extra | M8: =J3 -> 0
L9: (Buffer) | M9: =H34 -> 400000
A11: 6.1 | B11: Cold & Hot Commissioning + Trial Run - Staff | C11: 0 | D11: 0 | E11: 0 | F11: 0 | G11: 0 | H11: 0 | K11: =SUM(H11:J11) -> 0
A12: 6.1.1 | B12: Start-up personnel | C12: 5000000 | D12: 5000000 | E12: 5000000 | F12: 5000000 | G12: 5000000 | H12: 5000000 | K12: =SUM(H12:J12) -> 5000000
A13: 6.1.2 | B13: Boiler boiling | C13: 200000 | D13: 200000 | E13: 200000 | F13: 200000 | G13: 200000 | H13: 200000 | K13: =SUM(H13:J13) -> 200000
A14: 6.1.3 | B14: Steam blowing | C14: 550000 | D14: 550000 | E14: 550000 | F14: 550000 | G14: 550000 | H14: 550000 | K14: =SUM(H14:J14) -> 550000
A15: 6.1.4 | B15: Nitrogenation | C15: 50000 | D15: 50000 | E15: 50000 | F15: 50000 | G15: 50000 | H15: 50000 | K15: =SUM(H15:J15) -> 50000
C16: =SUM(C11:C15) -> 5800000 | D16: =SUM(D11:D15) -> 5800000 | E16: =SUM(E11:E15) -> 5800000 | F16: =SUM(F11:F15) -> 5800000 | G16: =SUM(G11:G15) -> 5800000 | H16: =SUM(H11:H15) -> 5800000 | I16: =SUM(I11:I15) -> 0 | J16: =SUM(J11:J15) -> 0 | K16: =SUM(K11:K15) -> 5800000
G17: =$F16-G16 -> 0 | H17: =$F16-H16 -> 0 | K17: =$F16-K16 -> 0
A19: 6.2 | B19: Media, reagents for start-up and commissioning | C19: 0 | D19: 0 | E19: 0 | F19: 0 | G19: 0 | H19: 0 | K19: =SUM(H19:J19) -> 0
A20: 6.2.1 | B20: Fuel (light oil) | C20: 500000 | D20: 500000 | E20: 500000 | F20: 500000 | G20: 500000 | H20: 500000 | K20: =SUM(H20:J20) -> 500000
A21: 6.2.2 | B21: Nitrogen cylinders | C21: 50000 | D21: 50000 | E21: 50000 | F21: 50000 | G21: 50000 | H21: 50000 | K21: =SUM(H21:J21) -> 50000
A22: 6.2.3 | B22: Handling and disposal of bottom and fly ash | C22: 150000 | D22: 150000 | E22: 150000 | F22: 150000 | G22: 150000 | H22: 150000 | K22: =SUM(H22:J22) -> 150000
A23: 6.2.4 | B23: Chemical supplies | C23: 50000 | D23: 50000 | E23: 50000 | F23: 50000 | G23: 50000 | H23: 50000 | K23: =SUM(H23:J23) -> 50000
A24: 6.2.5 | B24: Lime supplies | C24: 350000 | D24: 350000 | E24: 350000 | F24: 350000 | G24: 350000 | H24: 350000 | K24: =SUM(H24:J24) -> 350000
A25: 6.2.6 | B25: Active carbon supplies | C25: 200000 | D25: 200000 | E25: 200000 | F25: 200000 | G25: 200000 | H25: 200000 | K25: =SUM(H25:J25) -> 200000
A26: 6.2.7 | B26: Disposal of waste after testing - discharge of waste water | C26: 150000 | D26: 150000 | E26: 150000 | F26: 150000 | G26: 150000 | H26: 150000 | K26: =SUM(H26:J26) -> 150000
C27: =SUM(C19:C26) -> 1450000 | D27: =SUM(D19:D26) -> 1450000 | E27: =SUM(E19:E26) -> 1450000 | F27: =SUM(F19:F26) -> 1450000 | G27: =SUM(G19:G26) -> 1450000 | H27: =SUM(H19:H26) -> 1450000 | I27: =SUM(I19:I26) -> 0 | J27: =SUM(J19:J26) -> 0 | K27: =SUM(K19:K26) -> 1450000
G28: =$F27-G27 -> 0 | H28: =$F27-H27 -> 0 | K28: =$F27-K27 -> 0
A30: 6.3 | B30: Training | C30: 500000 | D30: 500000 | E30: 500000 | F30: 500000 | G30: 500000 | H30: 500000 | K30: =SUM(H30:J30) -> 500000
C31: =SUM(C30:C30) -> 500000 | D31: =SUM(D30:D30) -> 500000 | E31: =SUM(E30:E30) -> 500000 | F31: =SUM(F30:F30) -> 500000 | G31: =SUM(G30:G30) -> 500000 | H31: =SUM(H30:H30) -> 500000 | I31: =SUM(I30:I30) -> 0 | J31: =SUM(J30:J30) -> 0 | K31: =SUM(K30:K30) -> 500000
G32: =$F31-G31 -> 0 | H32: =$F31-H31 -> 0 | K32: =$F31-K31 -> 0
A34: 6.4 | B34: Spare parts (guarantee period 48 msc) | C34: 500000 | D34: 500000 | E34: 400000 | F34: 400000 | G34: 400000 | H34: 400000 | K34: =SUM(H34:J34) -> 400000
A35: 6.4.1 | B35: Warranty extension for electrical works | C35: 0 | D35: 0 | E35: 100000 | F35: 100000 | G35: 100000 | H35: 100000 | K35: =SUM(H35:J35) -> 100000 | L35: ELEKTROSERV - ZAP | M35: ok
C36: =SUM(C34:C35) -> 500000 | D36: =SUM(D34:D35) -> 500000 | E36: =SUM(E34:E35) -> 500000 | F36: =SUM(F34:F35) -> 500000 | G36: =SUM(G34:G35) -> 500000 | H36: =SUM(H34:H35) -> 500000 | I36: =SUM(I34:I35) -> 0 | J36: =SUM(J34:J35) -> 0 | K36: =SUM(K34:K35) -> 500000
G37: =$F36-G36 -> 0 | H37: =$F36-H36 -> 0 | K37: =$F36-K36 -> 0
A39: 6.5 | B39: Compliance tests and simulations of the generation module | C39: 150000 | D39: 150000 | E39: 150000 | F39: 150000 | G39: 150000 | H39: 150000 | K39: =SUM(H39:J39) -> 150000
C40: =SUM(C39) -> 150000 | D40: =SUM(D39) -> 150000 | E40: =SUM(E39) -> 150000 | F40: =SUM(F39) -> 150000 | G40: =SUM(G39) -> 150000 | H40: =SUM(H39) -> 150000 | I40: =SUM(I39) -> 0 | J40: =SUM(J39) -> 0 | K40: =SUM(K39) -> 150000
G41: =$F40-G40 -> 0 | H41: =$F40-H40 -> 0 | K41: =$F40-K40 -> 0
A43: 6.6 | B43: Operating instructions | C43: 100000 | D43: 100000 | E43: 100000 | F43: 100000 | G43: 100000 | H43: 100000 | K43: =SUM(H43:J43) -> 100000
C44: =SUM(C43) -> 100000 | D44: =SUM(D43) -> 100000 | E44: =SUM(E43) -> 100000 | F44: =SUM(F43) -> 100000 | G44: =SUM(G43) -> 100000 | H44: =SUM(H43) -> 100000 | I44: =SUM(I43) -> 0 | J44: =SUM(J43) -> 0 | K44: =SUM(K43) -> 100000
G45: =$F44-G44 -> 0 | H45: =$F44-H44 -> 0 | K45: =$F44-K44 -> 0

Sheet 7_Backup
C2: BUDGET APERTURA | D2: BUDGET 02 | E2: BUDGET 07 | F2: BUDGET 14 (B0 approvato Mar 26) | G2: BUDGET 17 | H2: BUDGET 19 | I2: ORDINATO EXTRA | J2: DA ORDINARE EXTRA | K2: TOTALE CON FORECAST | M2: =SUM(M5:M8) -> 952781
A3: 7 - 8 | B3: ALIGNMENT TO TCO VALUES / BACKUP | C3: =C13+C19 -> 952781 | D3: =D13+D19 -> 952781 | E3: =E13+E19 -> 952781 | F3: =F13+F19 -> 952781 | G3: =G13+G19 -> 952781 | H3: =H13+H19 -> 952781 | I3: =I13+I19 -> 0 | J3: =J13+J19 -> 0 | K3: =K13+K19 -> 952781
H4: =$F$3-H3 -> 0 | K4: =$F$3-K3 -> 0
L5: Ordered | M5: =H12+H17+H18 -> 723162.81
L6: Negotiation | M6: =H11+H16 -> 229618.19
D7: SAVINGS | J7: SAVINGS | L7: Planned | M7: 0
D8: EXTRA | J8: EXTRA | L8: Extra | M8: =J3 -> 0
L9: (Buffer) | M9: 0
A11: 7.1 | B11: Backup | C11: 538352 | D11: 216139.19 | E11: 216139.19 | F11: 216139.19 | G11: 216139.19 | H11: 216139.19 | K11: =SUM(H11:J11) -> 216139.19
A12: 7.1.1 | B12: Earthmoving robots - ECR 3 | C12: 0 | D12: 322212.81 | E12: 322212.81 | F12: 322212.81 | G12: 322212.81 | H12: 322212.81 | K12: =SUM(H12:J12) -> 322212.81 | L12: MAR-KOP Marcin Mierzwa | M12: 4502939064
C13: =SUM(C11:C12) -> 538352 | D13: =SUM(D11:D12) -> 538352 | E13: =SUM(E11:E12) -> 538352 | F13: =SUM(F11:F12) -> 538352 | G13: =SUM(G11:G12) -> 538352 | H13: =SUM(H11:H12) -> 538352 | I13: =SUM(I11:I12) -> 0 | J13: =SUM(J11:J12) -> 0 | K13: =SUM(K11:K12) -> 538352
G14: =$F13-G13 -> 0 | H14: =$F13-H13 -> 0 | K14: =$F13-K13 -> 0
A16: 8.1 | B16: Backup | C16: 414429 | D16: 14429 | E16: 13479 | F16: 13479 | G16: 13479 | H16: 13479 | K16: =SUM(H16:J16) -> 13479
A17: 8.1.1 | B17: Temporary traffic organization - ECD 34 | C17: 0 | D17: 0 | E17: 950 | F17: 950 | G17: 950 | H17: 950 | K17: =SUM(H17:J17) -> 950 | L17: PROJBUD | M17: 4502971480
A18: 8.1.2 | B18: Obtaining decisions and permits - ECR 4 | C18: 0 | D18: 400000 | E18: 400000 | F18: 400000 | G18: 400000 | H18: 400000 | K18: =SUM(H18:J18) -> 400000 | L18: KaBo | M18: 4502946461
C19: =SUM(C16:C18) -> 414429 | D19: =SUM(D16:D18) -> 414429 | E19: =SUM(E16:E18) -> 414429 | F19: =SUM(F16:F18) -> 414429 | G19: =SUM(G16:G18) -> 414429 | H19: =SUM(H16:H18) -> 414429 | I19: =SUM(I16:I18) -> 0 | J19: =SUM(J16:J18) -> 0 | K19: =SUM(K16:K18) -> 414429
G20: =$F19-G19 -> 0 | H20: =$F19-H19 -> 0 | K20: =$F19-K19 -> 0
